<?xml version="1.0" encoding="UTF-8"?>
<?xml-stylesheet type="text/xsl" href="default.xsl"?>
<fr:tree
toc="true"
numbered="true"
show-heading="true"
show-metadata="true"
expanded="true"
root="false"
xmlns:fr="http://www.jonmsterling.com/jms-005P.xml"><fr:frontmatter><fr:anchor>2254</fr:anchor><fr:addr
type="user">johnstone2002elephant</fr:addr><fr:route>johnstone2002elephant.xml</fr:route><fr:title
text="Sketches of an elephant: a topos theory compendium">Sketches of an elephant: a topos theory compendium</fr:title><fr:taxon>Reference</fr:taxon><fr:date><fr:year>2002</fr:year></fr:date><fr:authors><fr:author><fr:link
type="local"
href="peterjohnstone.xml"
addr="peterjohnstone"
title="Peter T. Johnstone">Peter T. Johnstone</fr:link></fr:author></fr:authors><fr:meta
name="venue">Oxford Logical Guides</fr:meta><fr:meta
name="bibtex"><![CDATA[@book{johnstone2002,
  author = {Johnstone, Peter T.},
  publisher = {Oxford Science Publications},
  year = {2002},
  number = {43},
  series = {Oxford Logical Guides},
  title = {Sketches of an Elephant: A Topos Theory Compendium: Volumes 1 and 2},
}]]></fr:meta></fr:frontmatter><fr:mainmatter /><fr:backmatter /></fr:tree>