<?xml version="1.0" encoding="UTF-8"?>
<?xml-stylesheet type="text/xsl" href="default.xsl"?>
<fr:tree
toc="true"
numbered="true"
show-heading="true"
show-metadata="true"
expanded="true"
root="false"
xmlns:fr="http://www.jonmsterling.com/jms-005P.xml"><fr:frontmatter><fr:anchor>503</fr:anchor><fr:addr
type="user">set-000S</fr:addr><fr:route>set-000S.xml</fr:route><fr:title
text="Functional extensionality">Functional extensionality</fr:title><fr:taxon>Proposition</fr:taxon><fr:date><fr:year>2024</fr:year><fr:month>10</fr:month><fr:day>20</fr:day></fr:date><fr:authors /></fr:frontmatter><fr:mainmatter><fr:p>Let <fr:tex
display="inline"><![CDATA[f,g\colon A\to B]]></fr:tex> be <fr:link
type="local"
href="set-000R.xml"
addr="set-000R"
title="Function">functions</fr:link>.
  Then <fr:tex
display="inline"><![CDATA[f = g]]></fr:tex> if and only if for all <fr:tex
display="inline"><![CDATA[a \in  A]]></fr:tex>, <fr:tex
display="inline"><![CDATA[f(a) = g(a)]]></fr:tex>.</fr:p>
    
      
      <fr:tree
toc="false"
numbered="true"
show-heading="true"
show-metadata="false"
expanded="true"
root="false"
xmlns:fr="http://www.jonmsterling.com/jms-005P.xml"><fr:frontmatter><fr:anchor>362</fr:anchor><fr:addr
type="machine">#257</fr:addr><fr:route>unstable-257.xml</fr:route><fr:taxon>Proof</fr:taxon><fr:date><fr:year>2024</fr:year><fr:month>10</fr:month><fr:day>20</fr:day></fr:date><fr:authors /></fr:frontmatter><fr:mainmatter>
  The if direction is trivial.
  For the only if direction, assume that <fr:tex
display="inline"><![CDATA[f(a) = g(a)]]></fr:tex> for all <fr:tex
display="inline"><![CDATA[a \in  A]]></fr:tex>.
  By <fr:link
type="local"
href="set-0001.xml"
addr="set-0001"
title="Axiom of extensionality">extensionality</fr:link>, it suffices to show that for any <fr:tex
display="inline"><![CDATA[(a,b) \in  A \times  B]]></fr:tex>, <fr:tex
display="inline"><![CDATA[(a,b) \in  f]]></fr:tex> if and only if <fr:tex
display="inline"><![CDATA[(a,b) \in  g]]></fr:tex>.
  Suppose that <fr:tex
display="inline"><![CDATA[(a,b) \in  f]]></fr:tex>, then by <fr:link
type="local"
href="set-000O.xml"
addr="set-000O"
title="Functional relation">functionality</fr:link>, <fr:tex
display="inline"><![CDATA[b = f(a)]]></fr:tex>.
  By <fr:link
type="local"
href="set-000N.xml"
addr="set-000N"
title="Total relation">totality</fr:link>, <fr:tex
display="inline"><![CDATA[(a,g(a)) \in  g]]></fr:tex>.
  By hypothesis, <fr:tex
display="inline"><![CDATA[(a,f(a)) = (a,g(a))]]></fr:tex>.
  Thus, <fr:tex
display="inline"><![CDATA[(a,f(a)) \in  g]]></fr:tex>.
  The converse is analogous.
</fr:mainmatter><fr:backmatter /></fr:tree>
    
  </fr:mainmatter><fr:backmatter><fr:tree
toc="false"
numbered="false"
show-heading="true"
show-metadata="false"
expanded="true"
root="false"
xmlns:fr="http://www.jonmsterling.com/jms-005P.xml"><fr:frontmatter><fr:title
text="Context">Context</fr:title><fr:authors /></fr:frontmatter><fr:mainmatter><fr:tree
toc="true"
numbered="false"
show-heading="true"
show-metadata="true"
expanded="false"
root="false"
xmlns:fr="http://www.jonmsterling.com/jms-005P.xml"><fr:frontmatter><fr:anchor>504</fr:anchor><fr:addr
type="user">set-000D</fr:addr><fr:route>set-000D.xml</fr:route><fr:title
text="Zermelo-Fraenkel set theory">Zermelo-Fraenkel set theory</fr:title><fr:taxon>Section</fr:taxon><fr:date><fr:year>2024</fr:year><fr:month>10</fr:month><fr:day>20</fr:day></fr:date><fr:authors /></fr:frontmatter><fr:mainmatter>
  <fr:tree
toc="true"
numbered="true"
show-heading="true"
show-metadata="false"
expanded="true"
root="false"
xmlns:fr="http://www.jonmsterling.com/jms-005P.xml"><fr:frontmatter><fr:anchor>327</fr:anchor><fr:addr
type="machine">#265</fr:addr><fr:route>unstable-265.xml</fr:route><fr:title
text="Axioms of ZF">Axioms of ZF</fr:title><fr:date><fr:year>2024</fr:year><fr:month>10</fr:month><fr:day>20</fr:day></fr:date><fr:authors /></fr:frontmatter><fr:mainmatter><fr:tree
toc="true"
numbered="true"
show-heading="true"
show-metadata="false"
expanded="true"
root="false"
xmlns:fr="http://www.jonmsterling.com/jms-005P.xml"><fr:frontmatter><fr:anchor>328</fr:anchor><fr:addr
type="user">set-0001</fr:addr><fr:route>set-0001.xml</fr:route><fr:title
text="Axiom of extensionality">Axiom of extensionality</fr:title><fr:taxon>Axiom</fr:taxon><fr:date><fr:year>2024</fr:year><fr:month>9</fr:month><fr:day>15</fr:day></fr:date><fr:authors /></fr:frontmatter><fr:mainmatter><fr:p>Two sets are equal iff they have the same elements.</fr:p><fr:tex
display="block"><![CDATA[   \forall x,y.\mkern 5mux = y \Leftrightarrow  \forall z.\mkern 5muz \in  x \Leftrightarrow  z \in  y ]]></fr:tex></fr:mainmatter><fr:backmatter /></fr:tree><fr:tree
toc="true"
numbered="true"
show-heading="true"
show-metadata="false"
expanded="true"
root="false"
xmlns:fr="http://www.jonmsterling.com/jms-005P.xml"><fr:frontmatter><fr:anchor>329</fr:anchor><fr:addr
type="user">set-0002</fr:addr><fr:route>set-0002.xml</fr:route><fr:title
text="Axiom of empty set">Axiom of empty set</fr:title><fr:taxon>Axiom</fr:taxon><fr:date><fr:year>2024</fr:year><fr:month>9</fr:month><fr:day>15</fr:day></fr:date><fr:authors /></fr:frontmatter><fr:mainmatter><fr:p>The empty set <fr:tex
display="inline"><![CDATA[\varnothing ]]></fr:tex> exists.</fr:p><fr:tex
display="block"><![CDATA[   \exists x.\mkern 5mu\forall y.\mkern 5muy \notin  x ]]></fr:tex></fr:mainmatter><fr:backmatter /></fr:tree><fr:tree
toc="true"
numbered="true"
show-heading="true"
show-metadata="false"
expanded="true"
root="false"
xmlns:fr="http://www.jonmsterling.com/jms-005P.xml"><fr:frontmatter><fr:anchor>330</fr:anchor><fr:addr
type="user">set-0003</fr:addr><fr:route>set-0003.xml</fr:route><fr:title
text="Axiom of pairing">Axiom of pairing</fr:title><fr:taxon>Axiom</fr:taxon><fr:date><fr:year>2024</fr:year><fr:month>9</fr:month><fr:day>15</fr:day></fr:date><fr:authors /></fr:frontmatter><fr:mainmatter><fr:p>For any two set <fr:tex
display="inline"><![CDATA[x]]></fr:tex> and <fr:tex
display="inline"><![CDATA[y]]></fr:tex>, the set <fr:tex
display="inline"><![CDATA[\{x,y\}]]></fr:tex> exists.</fr:p><fr:tex
display="block"><![CDATA[   \forall x,y.\mkern 5mu\exists p.\mkern 5mu\forall z.\mkern 5muz \in  p \Leftrightarrow  z = x \vee  z = y ]]></fr:tex></fr:mainmatter><fr:backmatter /></fr:tree><fr:tree
toc="true"
numbered="true"
show-heading="true"
show-metadata="false"
expanded="true"
root="false"
xmlns:fr="http://www.jonmsterling.com/jms-005P.xml"><fr:frontmatter><fr:anchor>331</fr:anchor><fr:addr
type="user">set-0005</fr:addr><fr:route>set-0005.xml</fr:route><fr:title
text="Axiom schema of separation">Axiom schema of separation</fr:title><fr:taxon>Axiom</fr:taxon><fr:date><fr:year>2024</fr:year><fr:month>9</fr:month><fr:day>15</fr:day></fr:date><fr:authors /></fr:frontmatter><fr:mainmatter><fr:p>Let <fr:tex
display="inline"><![CDATA[\varphi ]]></fr:tex> be any formula in the language of ZF set theory with free variables among <fr:tex
display="inline"><![CDATA[x]]></fr:tex>, <fr:tex
display="inline"><![CDATA[z]]></fr:tex>, <fr:tex
display="inline"><![CDATA[p_{1},\ldots ,p_{n}]]></fr:tex> and <fr:tex
display="inline"><![CDATA[x]]></fr:tex> be a set.
  The set <fr:tex
display="inline"><![CDATA[\{z \in  x \mid  \varphi (x,p_{1},\ldots ,p_{n},z)\}]]></fr:tex> exists.</fr:p><fr:tex
display="block"><![CDATA[   \forall x,p_{1},\ldots ,p_{n}.\mkern 5mu\exists y.\mkern 5mu\forall z.\mkern 5muz \in  y \Leftrightarrow  z \in  x \wedge  \varphi (x,p_{1},\ldots ,p_{n},z) ]]></fr:tex></fr:mainmatter><fr:backmatter /></fr:tree><fr:tree
toc="true"
numbered="true"
show-heading="true"
show-metadata="false"
expanded="true"
root="false"
xmlns:fr="http://www.jonmsterling.com/jms-005P.xml"><fr:frontmatter><fr:anchor>332</fr:anchor><fr:addr
type="user">set-0006</fr:addr><fr:route>set-0006.xml</fr:route><fr:title
text="Axiom of powerset">Axiom of powerset</fr:title><fr:taxon>Axiom</fr:taxon><fr:date><fr:year>2024</fr:year><fr:month>9</fr:month><fr:day>15</fr:day></fr:date><fr:authors /></fr:frontmatter><fr:mainmatter><fr:p>For any set <fr:tex
display="inline"><![CDATA[x]]></fr:tex>, the powerset <fr:tex
display="inline"><![CDATA[P(x)]]></fr:tex> is a set.</fr:p><fr:tex
display="block"><![CDATA[   \forall x.\mkern 5mu\exists p.\mkern 5mu\forall y.\mkern 5muy \in  p \Leftrightarrow  \forall z.\mkern 5muz \in  y \Rightarrow  z \in  x ]]></fr:tex></fr:mainmatter><fr:backmatter /></fr:tree><fr:tree
toc="true"
numbered="true"
show-heading="true"
show-metadata="false"
expanded="true"
root="false"
xmlns:fr="http://www.jonmsterling.com/jms-005P.xml"><fr:frontmatter><fr:anchor>333</fr:anchor><fr:addr
type="user">set-0004</fr:addr><fr:route>set-0004.xml</fr:route><fr:title
text="Axiom of union">Axiom of union</fr:title><fr:taxon>Axiom</fr:taxon><fr:date><fr:year>2024</fr:year><fr:month>9</fr:month><fr:day>15</fr:day></fr:date><fr:authors /></fr:frontmatter><fr:mainmatter><fr:p>Given a set <fr:tex
display="inline"><![CDATA[x]]></fr:tex> (of sets), the union <fr:tex
display="inline"><![CDATA[\bigcup  x]]></fr:tex> exists.</fr:p><fr:tex
display="block"><![CDATA[   \forall x.\mkern 5mu\exists y.\mkern 5mu\forall z.\mkern 5muz \in  y \Leftrightarrow  \exists v.\mkern 5muv \in  x \wedge  z \in  v ]]></fr:tex></fr:mainmatter><fr:backmatter /></fr:tree><fr:tree
toc="true"
numbered="true"
show-heading="true"
show-metadata="false"
expanded="true"
root="false"
xmlns:fr="http://www.jonmsterling.com/jms-005P.xml"><fr:frontmatter><fr:anchor>334</fr:anchor><fr:addr
type="user">set-0007</fr:addr><fr:route>set-0007.xml</fr:route><fr:title
text="Axiom of infinity">Axiom of infinity</fr:title><fr:taxon>Axiom</fr:taxon><fr:date><fr:year>2024</fr:year><fr:month>9</fr:month><fr:day>15</fr:day></fr:date><fr:authors /></fr:frontmatter><fr:mainmatter><fr:p>An inductive set exists.</fr:p><fr:tex
display="block"><![CDATA[   \exists x.\mkern 5mu\varnothing  \in  x \wedge  \forall y.\mkern 5muy \in  x \Rightarrow  y \cup  \{y\} \in  x ]]></fr:tex></fr:mainmatter><fr:backmatter /></fr:tree><fr:tree
toc="true"
numbered="true"
show-heading="true"
show-metadata="false"
expanded="true"
root="false"
xmlns:fr="http://www.jonmsterling.com/jms-005P.xml"><fr:frontmatter><fr:anchor>335</fr:anchor><fr:addr
type="user">set-0008</fr:addr><fr:route>set-0008.xml</fr:route><fr:title
text="Axiom schema of replacement">Axiom schema of replacement</fr:title><fr:taxon>Axiom</fr:taxon><fr:date><fr:year>2024</fr:year><fr:month>9</fr:month><fr:day>18</fr:day></fr:date><fr:authors /></fr:frontmatter><fr:mainmatter><fr:p>The image of every definable function is a set.</fr:p><fr:tex
display="block"><![CDATA[   (\forall x.\mkern 5mu\exists y.\mkern 5mu\varphi (x,y)) \wedge  (\forall x,y,y'.\mkern 5mu\varphi (x,y) \wedge  \varphi (x,y') \Rightarrow  y = y') \Rightarrow \\   \forall u.\mkern 5mu\exists v.\mkern 5mu\forall y.\mkern 5muy \in  v \Leftrightarrow  \exists x.\mkern 5mux \in  u \Rightarrow  \varphi (x,y) ]]></fr:tex></fr:mainmatter><fr:backmatter /></fr:tree><fr:tree
toc="true"
numbered="true"
show-heading="true"
show-metadata="false"
expanded="true"
root="false"
xmlns:fr="http://www.jonmsterling.com/jms-005P.xml"><fr:frontmatter><fr:anchor>336</fr:anchor><fr:addr
type="user">set-0009</fr:addr><fr:route>set-0009.xml</fr:route><fr:title
text="Axiom of foundation">Axiom of foundation</fr:title><fr:taxon>Axiom</fr:taxon><fr:date><fr:year>2024</fr:year><fr:month>9</fr:month><fr:day>18</fr:day></fr:date><fr:authors /></fr:frontmatter><fr:mainmatter><fr:p><fr:tex
display="inline"><![CDATA[\forall x.\mkern 5mu(\exists y.\mkern 5muy \in  x) \Rightarrow  \exists z.\mkern 5muz \in  x \wedge  (\lnot \exists a.\mkern 5mua \in  x \wedge  a \in  z)]]></fr:tex></fr:p></fr:mainmatter><fr:backmatter /></fr:tree></fr:mainmatter><fr:backmatter /></fr:tree>

  <fr:tree
toc="true"
numbered="true"
show-heading="true"
show-metadata="false"
expanded="true"
root="false"
xmlns:fr="http://www.jonmsterling.com/jms-005P.xml"><fr:frontmatter><fr:anchor>337</fr:anchor><fr:addr
type="machine">#266</fr:addr><fr:route>unstable-266.xml</fr:route><fr:title
text="Basic consequences of ZF">Basic consequences of ZF</fr:title><fr:date><fr:year>2024</fr:year><fr:month>10</fr:month><fr:day>20</fr:day></fr:date><fr:authors /></fr:frontmatter><fr:mainmatter><fr:tree
toc="true"
numbered="true"
show-heading="true"
show-metadata="false"
expanded="true"
root="false"
xmlns:fr="http://www.jonmsterling.com/jms-005P.xml"><fr:frontmatter><fr:anchor>338</fr:anchor><fr:addr
type="user">set-000F</fr:addr><fr:route>set-000F.xml</fr:route><fr:title
text="Uniqueness of the empty set">Uniqueness of the empty set</fr:title><fr:taxon>Proposition</fr:taxon><fr:date><fr:year>2024</fr:year><fr:month>10</fr:month><fr:day>20</fr:day></fr:date><fr:authors /></fr:frontmatter><fr:mainmatter><fr:p>The empty set <fr:tex
display="inline"><![CDATA[\varnothing ]]></fr:tex> is unique.</fr:p>
    
      
      <fr:tree
toc="false"
numbered="true"
show-heading="true"
show-metadata="false"
expanded="true"
root="false"
xmlns:fr="http://www.jonmsterling.com/jms-005P.xml"><fr:frontmatter><fr:anchor>339</fr:anchor><fr:addr
type="machine">#263</fr:addr><fr:route>unstable-263.xml</fr:route><fr:taxon>Proof</fr:taxon><fr:date><fr:year>2024</fr:year><fr:month>10</fr:month><fr:day>20</fr:day></fr:date><fr:authors /></fr:frontmatter><fr:mainmatter>
  Let <fr:tex
display="inline"><![CDATA[E]]></fr:tex> be a set such that <fr:tex
display="inline"><![CDATA[\forall y.\mkern 5muy \notin  E]]></fr:tex>.
  By <fr:link
type="local"
href="set-0001.xml"
addr="set-0001"
title="Axiom of extensionality">extensionality</fr:link>, it suffices to show that <fr:tex
display="inline"><![CDATA[\forall y.\mkern 5muy \in  \varnothing  \Leftrightarrow  y \in  E]]></fr:tex>, but this holds vacuously.
</fr:mainmatter><fr:backmatter /></fr:tree>
    
  </fr:mainmatter><fr:backmatter /></fr:tree><fr:tree
toc="true"
numbered="true"
show-heading="true"
show-metadata="false"
expanded="true"
root="false"
xmlns:fr="http://www.jonmsterling.com/jms-005P.xml"><fr:frontmatter><fr:anchor>340</fr:anchor><fr:addr
type="user">set-000G</fr:addr><fr:route>set-000G.xml</fr:route><fr:title
text="Uniqueness of pairing">Uniqueness of pairing</fr:title><fr:taxon>Proposition</fr:taxon><fr:date><fr:year>2024</fr:year><fr:month>10</fr:month><fr:day>20</fr:day></fr:date><fr:authors /></fr:frontmatter><fr:mainmatter><fr:p>Let <fr:tex
display="inline"><![CDATA[x,y]]></fr:tex> be sets.
  Then the set <fr:tex
display="inline"><![CDATA[{\mathopen {}\{x,y\}\mathclose {}}]]></fr:tex> is unique.</fr:p>
    
      
      <fr:tree
toc="false"
numbered="true"
show-heading="true"
show-metadata="false"
expanded="true"
root="false"
xmlns:fr="http://www.jonmsterling.com/jms-005P.xml"><fr:frontmatter><fr:anchor>341</fr:anchor><fr:addr
type="machine">#262</fr:addr><fr:route>unstable-262.xml</fr:route><fr:taxon>Proof</fr:taxon><fr:date><fr:year>2024</fr:year><fr:month>10</fr:month><fr:day>20</fr:day></fr:date><fr:authors /></fr:frontmatter><fr:mainmatter>
  Let <fr:tex
display="inline"><![CDATA[P]]></fr:tex> be a set such that <fr:tex
display="inline"><![CDATA[\forall a.\mkern 5mua \in  P \Leftrightarrow  a = x \vee  a = y]]></fr:tex>.
  It suffices, by <fr:link
type="local"
href="set-0001.xml"
addr="set-0001"
title="Axiom of extensionality">extensionality</fr:link>, to show that <fr:tex
display="inline"><![CDATA[\forall b.\mkern 5mub \in  {\mathopen {}\{x,y\}\mathclose {}} \Leftrightarrow  b \in  P]]></fr:tex>.

  If <fr:tex
display="inline"><![CDATA[b \in  {\mathopen {}\{x,y\}\mathclose {}}]]></fr:tex>, then by <fr:link
type="local"
href="set-0003.xml"
addr="set-0003"
title="Axiom of pairing">pairing</fr:link>, <fr:tex
display="inline"><![CDATA[b = x]]></fr:tex> or <fr:tex
display="inline"><![CDATA[b = y]]></fr:tex>.
  Thus, it follows that <fr:tex
display="inline"><![CDATA[b \in  P]]></fr:tex>.
  The converse is completely analogous.
</fr:mainmatter><fr:backmatter /></fr:tree>
    
  </fr:mainmatter><fr:backmatter /></fr:tree><fr:tree
toc="true"
numbered="true"
show-heading="true"
show-metadata="false"
expanded="true"
root="false"
xmlns:fr="http://www.jonmsterling.com/jms-005P.xml"><fr:frontmatter><fr:anchor>342</fr:anchor><fr:addr
type="user">set-000H</fr:addr><fr:route>set-000H.xml</fr:route><fr:title
text="Existence of singletons">Existence of singletons</fr:title><fr:taxon>Proposition</fr:taxon><fr:date><fr:year>2024</fr:year><fr:month>10</fr:month><fr:day>20</fr:day></fr:date><fr:authors /></fr:frontmatter><fr:mainmatter><fr:p>For any set <fr:tex
display="inline"><![CDATA[x]]></fr:tex>, the set <fr:tex
display="inline"><![CDATA[{\mathopen {}\{x\}\mathclose {}}]]></fr:tex> exists.</fr:p>
    
      
      <fr:tree
toc="false"
numbered="true"
show-heading="true"
show-metadata="false"
expanded="true"
root="false"
xmlns:fr="http://www.jonmsterling.com/jms-005P.xml"><fr:frontmatter><fr:anchor>343</fr:anchor><fr:addr
type="machine">#261</fr:addr><fr:route>unstable-261.xml</fr:route><fr:taxon>Proof</fr:taxon><fr:date><fr:year>2024</fr:year><fr:month>10</fr:month><fr:day>20</fr:day></fr:date><fr:authors /></fr:frontmatter><fr:mainmatter>
  By <fr:link
type="local"
href="set-0003.xml"
addr="set-0003"
title="Axiom of pairing">pairing</fr:link>, there is a set <fr:tex
display="inline"><![CDATA[p]]></fr:tex> such that <fr:tex
display="inline"><![CDATA[\forall a.\mkern 5mua \in  p \Leftrightarrow  a = x \vee  a = x]]></fr:tex>, or equivalently, <fr:tex
display="inline"><![CDATA[\forall a.\mkern 5mua \in  p \Leftrightarrow  a = x]]></fr:tex>.
</fr:mainmatter><fr:backmatter /></fr:tree>
    
  </fr:mainmatter><fr:backmatter /></fr:tree><fr:tree
toc="true"
numbered="true"
show-heading="true"
show-metadata="false"
expanded="true"
root="false"
xmlns:fr="http://www.jonmsterling.com/jms-005P.xml"><fr:frontmatter><fr:anchor>344</fr:anchor><fr:addr
type="user">set-000X</fr:addr><fr:route>set-000X.xml</fr:route><fr:title
text="The membership relation is irreflexive">The membership relation is irreflexive</fr:title><fr:taxon>Proposition</fr:taxon><fr:date><fr:year>2024</fr:year><fr:month>10</fr:month><fr:day>20</fr:day></fr:date><fr:authors /></fr:frontmatter><fr:mainmatter><fr:p>For any set <fr:tex
display="inline"><![CDATA[x]]></fr:tex>, <fr:tex
display="inline"><![CDATA[x \notin  x]]></fr:tex>.</fr:p>
    
      
      <fr:tree
toc="false"
numbered="true"
show-heading="true"
show-metadata="false"
expanded="true"
root="false"
xmlns:fr="http://www.jonmsterling.com/jms-005P.xml"><fr:frontmatter><fr:anchor>345</fr:anchor><fr:addr
type="machine">#252</fr:addr><fr:route>unstable-252.xml</fr:route><fr:taxon>Proof</fr:taxon><fr:date><fr:year>2024</fr:year><fr:month>10</fr:month><fr:day>20</fr:day></fr:date><fr:authors /></fr:frontmatter><fr:mainmatter>
  Let <fr:tex
display="inline"><![CDATA[x]]></fr:tex> be a set.
  Suppose that <fr:tex
display="inline"><![CDATA[x \in  x]]></fr:tex>.
  Consider <fr:tex
display="inline"><![CDATA[{\mathopen {}\{x\}\mathclose {}}]]></fr:tex>.
  This is a non-empty set, so <fr:link
type="local"
href="set-0009.xml"
addr="set-0009"
title="Axiom of foundation">foundation</fr:link> implies that there is a set <fr:tex
display="inline"><![CDATA[z \in  {\mathopen {}\{x\}\mathclose {}}]]></fr:tex> such that <fr:tex
display="inline"><![CDATA[z \cap  {\mathopen {}\{x\}\mathclose {}} = \varnothing ]]></fr:tex>.
  By <fr:ref
addr="set-000H"
href="set-000H.xml"
taxon="Proposition" />, <fr:tex
display="inline"><![CDATA[z = x]]></fr:tex>.
  Then since <fr:tex
display="inline"><![CDATA[x \in  x]]></fr:tex>, we have that <fr:tex
display="inline"><![CDATA[x \in  z]]></fr:tex>.
  Thus, <fr:tex
display="inline"><![CDATA[x \in  z \cap  {\mathopen {}\{x\}\mathclose {}}]]></fr:tex>, which is a contradiction.
</fr:mainmatter><fr:backmatter /></fr:tree>
    
  </fr:mainmatter><fr:backmatter /></fr:tree></fr:mainmatter><fr:backmatter /></fr:tree>

  <fr:tree
toc="true"
numbered="true"
show-heading="true"
show-metadata="false"
expanded="true"
root="false"
xmlns:fr="http://www.jonmsterling.com/jms-005P.xml"><fr:frontmatter><fr:anchor>346</fr:anchor><fr:addr
type="machine">#267</fr:addr><fr:route>unstable-267.xml</fr:route><fr:title
text="Ordered pairs">Ordered pairs</fr:title><fr:date><fr:year>2024</fr:year><fr:month>10</fr:month><fr:day>20</fr:day></fr:date><fr:authors /></fr:frontmatter><fr:mainmatter><fr:tree
toc="true"
numbered="true"
show-heading="true"
show-metadata="false"
expanded="true"
root="false"
xmlns:fr="http://www.jonmsterling.com/jms-005P.xml"><fr:frontmatter><fr:anchor>347</fr:anchor><fr:addr
type="user">set-000I</fr:addr><fr:route>set-000I.xml</fr:route><fr:title
text="Ordered pairs">Ordered pairs</fr:title><fr:taxon>Definition</fr:taxon><fr:date><fr:year>2024</fr:year><fr:month>10</fr:month><fr:day>20</fr:day></fr:date><fr:authors /></fr:frontmatter><fr:mainmatter><fr:p>Let <fr:tex
display="inline"><![CDATA[x,y]]></fr:tex> be sets.
  We define the <fr:em><fr:strong>ordered pair</fr:strong></fr:em> <fr:tex
display="inline"><![CDATA[(x,y)]]></fr:tex> as the set <fr:tex
display="inline"><![CDATA[{\mathopen {}\{{\mathopen {}\{x\}\mathclose {}},{\mathopen {}\{x,y\}\mathclose {}}\}\mathclose {}}]]></fr:tex>.</fr:p></fr:mainmatter><fr:backmatter /></fr:tree><fr:tree
toc="true"
numbered="true"
show-heading="true"
show-metadata="false"
expanded="true"
root="false"
xmlns:fr="http://www.jonmsterling.com/jms-005P.xml"><fr:frontmatter><fr:anchor>348</fr:anchor><fr:addr
type="user">set-000J</fr:addr><fr:route>set-000J.xml</fr:route><fr:title
text="Existence of ordered pairs">Existence of <fr:link
type="local"
href="set-000I.xml"
addr="set-000I"
title="Ordered pairs">ordered pairs</fr:link></fr:title><fr:taxon>Proposition</fr:taxon><fr:date><fr:year>2024</fr:year><fr:month>10</fr:month><fr:day>20</fr:day></fr:date><fr:authors /></fr:frontmatter><fr:mainmatter><fr:p>Let <fr:tex
display="inline"><![CDATA[x,y]]></fr:tex> be sets.
  The ordered pair <fr:tex
display="inline"><![CDATA[(x,y)]]></fr:tex> exists.</fr:p>
    
      
      <fr:tree
toc="false"
numbered="true"
show-heading="true"
show-metadata="false"
expanded="true"
root="false"
xmlns:fr="http://www.jonmsterling.com/jms-005P.xml"><fr:frontmatter><fr:anchor>349</fr:anchor><fr:addr
type="machine">#260</fr:addr><fr:route>unstable-260.xml</fr:route><fr:taxon>Proof</fr:taxon><fr:date><fr:year>2024</fr:year><fr:month>10</fr:month><fr:day>20</fr:day></fr:date><fr:authors /></fr:frontmatter><fr:mainmatter>
  By <fr:ref
addr="set-000H"
href="set-000H.xml"
taxon="Proposition" />, <fr:tex
display="inline"><![CDATA[{\mathopen {}\{x\}\mathclose {}}]]></fr:tex> exists.
  By <fr:link
type="local"
href="set-0003.xml"
addr="set-0003"
title="Axiom of pairing">pairing</fr:link>, <fr:tex
display="inline"><![CDATA[{\mathopen {}\{x,y\}\mathclose {}}]]></fr:tex> exists.
  By <fr:link
type="local"
href="set-0003.xml"
addr="set-0003"
title="Axiom of pairing">pairing</fr:link> again, <fr:tex
display="inline"><![CDATA[{\mathopen {}\{{\mathopen {}\{x\}\mathclose {}},{\mathopen {}\{x,y\}\mathclose {}}\}\mathclose {}}]]></fr:tex> exists.
</fr:mainmatter><fr:backmatter /></fr:tree>
    
  </fr:mainmatter><fr:backmatter /></fr:tree><fr:tree
toc="true"
numbered="true"
show-heading="true"
show-metadata="false"
expanded="true"
root="false"
xmlns:fr="http://www.jonmsterling.com/jms-005P.xml"><fr:frontmatter><fr:anchor>350</fr:anchor><fr:addr
type="user">set-000K</fr:addr><fr:route>set-000K.xml</fr:route><fr:title
text="Ordered pair property"><fr:link
type="local"
href="set-000I.xml"
addr="set-000I"
title="Ordered pairs">Ordered pair</fr:link> property</fr:title><fr:taxon>Proposition</fr:taxon><fr:date><fr:year>2024</fr:year><fr:month>10</fr:month><fr:day>20</fr:day></fr:date><fr:authors /></fr:frontmatter><fr:mainmatter><fr:p>Let <fr:tex
display="inline"><![CDATA[x,y,a,b]]></fr:tex> be sets.
  Then <fr:tex
display="inline"><![CDATA[(x,y) = (a,b)]]></fr:tex> if and only if <fr:tex
display="inline"><![CDATA[x = a]]></fr:tex> and <fr:tex
display="inline"><![CDATA[y = b]]></fr:tex>.</fr:p>
    
      
      <fr:tree
toc="false"
numbered="true"
show-heading="true"
show-metadata="false"
expanded="true"
root="false"
xmlns:fr="http://www.jonmsterling.com/jms-005P.xml"><fr:frontmatter><fr:anchor>351</fr:anchor><fr:addr
type="machine">#259</fr:addr><fr:route>unstable-259.xml</fr:route><fr:taxon>Proof</fr:taxon><fr:date><fr:year>2024</fr:year><fr:month>10</fr:month><fr:day>20</fr:day></fr:date><fr:authors /></fr:frontmatter><fr:mainmatter>
  <fr:p>The only if direction is completely trivial.
    Assume that <fr:tex
display="inline"><![CDATA[(x,y) = (a,b)]]></fr:tex>.
    First, we claim that <fr:tex
display="inline"><![CDATA[x = a]]></fr:tex>.
    By definition, we have <fr:tex
display="inline"><![CDATA[{\mathopen {}\{{\mathopen {}\{x\}\mathclose {}},{\mathopen {}\{x,y\}\mathclose {}}\}\mathclose {}} = {\mathopen {}\{{\mathopen {}\{a\}\mathclose {}},{\mathopen {}\{a,b\}\mathclose {}}\}\mathclose {}}]]></fr:tex>.
    By <fr:link
type="local"
href="set-0001.xml"
addr="set-0001"
title="Axiom of extensionality">extensionality</fr:link>, <fr:tex
display="inline"><![CDATA[{\mathopen {}\{x\}\mathclose {}} \in  {\mathopen {}\{{\mathopen {}\{a\}\mathclose {}},{\mathopen {}\{a,b\}\mathclose {}}\}\mathclose {}}]]></fr:tex>.
    By <fr:link
type="local"
href="set-0003.xml"
addr="set-0003"
title="Axiom of pairing">pairing</fr:link>, either <fr:tex
display="inline"><![CDATA[{\mathopen {}\{x\}\mathclose {}} = {\mathopen {}\{a\}\mathclose {}}]]></fr:tex> or <fr:tex
display="inline"><![CDATA[{\mathopen {}\{x\}\mathclose {}} = {\mathopen {}\{a,b\}\mathclose {}}]]></fr:tex>.
    In the former case, <fr:tex
display="inline"><![CDATA[x = a]]></fr:tex> follows as a consequence of <fr:link
type="local"
href="set-0003.xml"
addr="set-0003"
title="Axiom of pairing">pairing</fr:link>.
    In the latter case, we have <fr:tex
display="inline"><![CDATA[a \in  {\mathopen {}\{x\}\mathclose {}}]]></fr:tex> and <fr:tex
display="inline"><![CDATA[b \in  {\mathopen {}\{x\}\mathclose {}}]]></fr:tex> as a consequence of <fr:link
type="local"
href="set-0001.xml"
addr="set-0001"
title="Axiom of extensionality">extensionality</fr:link>.
    Then by <fr:link
type="local"
href="set-0003.xml"
addr="set-0003"
title="Axiom of pairing">pairing</fr:link>, we have <fr:tex
display="inline"><![CDATA[x = a = b]]></fr:tex>.</fr:p>
  <fr:p>It remains to show that <fr:tex
display="inline"><![CDATA[y = b]]></fr:tex>.
    In this case, as a consequence of <fr:link
type="local"
href="set-0001.xml"
addr="set-0001"
title="Axiom of extensionality">extensionality</fr:link>, consider <fr:tex
display="inline"><![CDATA[{\mathopen {}\{x,y\}\mathclose {}} \in  {\mathopen {}\{{\mathopen {}\{a\}\mathclose {}},{\mathopen {}\{a,b\}\mathclose {}}\}\mathclose {}}]]></fr:tex>.
    By <fr:link
type="local"
href="set-0003.xml"
addr="set-0003"
title="Axiom of pairing">pairing</fr:link>, either <fr:tex
display="inline"><![CDATA[{\mathopen {}\{x,y\}\mathclose {}} = {\mathopen {}\{a\}\mathclose {}}]]></fr:tex> or <fr:tex
display="inline"><![CDATA[{\mathopen {}\{x,y\}\mathclose {}} = {\mathopen {}\{a,b\}\mathclose {}}]]></fr:tex>.
    In the former case, we have <fr:tex
display="inline"><![CDATA[x = y = a]]></fr:tex> as a consequence of <fr:link
type="local"
href="set-0001.xml"
addr="set-0001"
title="Axiom of extensionality">extensionality</fr:link> and <fr:link
type="local"
href="set-0003.xml"
addr="set-0003"
title="Axiom of pairing">pairing</fr:link>.
    Thus, <fr:tex
display="inline"><![CDATA[{\mathopen {}\{{\mathopen {}\{x\}\mathclose {}},{\mathopen {}\{x,y\}\mathclose {}}\}\mathclose {}} = {\mathopen {}\{{\mathopen {}\{x\}\mathclose {}},{\mathopen {}\{x\}\mathclose {}}\}\mathclose {}} = {\mathopen {}\{{\mathopen {}\{x\}\mathclose {}}\}\mathclose {}} = {\mathopen {}\{{\mathopen {}\{a\}\mathclose {}},{\mathopen {}\{a,b\}\mathclose {}}\}\mathclose {}}]]></fr:tex> demands that <fr:tex
display="inline"><![CDATA[a = b]]></fr:tex>.
    In the latter case, if <fr:tex
display="inline"><![CDATA[y = a]]></fr:tex> then <fr:tex
display="inline"><![CDATA[{\mathopen {}\{x,y\}\mathclose {}} = {\mathopen {}\{a,y\}\mathclose {}} = {\mathopen {}\{a\}\mathclose {}} = {\mathopen {}\{a,b\}\mathclose {}}]]></fr:tex> demands that <fr:tex
display="inline"><![CDATA[a = b]]></fr:tex>.
    But, if <fr:tex
display="inline"><![CDATA[y = b]]></fr:tex> then there is nothing left to prove.</fr:p>
</fr:mainmatter><fr:backmatter /></fr:tree>
    
  </fr:mainmatter><fr:backmatter /></fr:tree><fr:tree
toc="true"
numbered="true"
show-heading="true"
show-metadata="false"
expanded="true"
root="false"
xmlns:fr="http://www.jonmsterling.com/jms-005P.xml"><fr:frontmatter><fr:anchor>352</fr:anchor><fr:addr
type="user">set-000L</fr:addr><fr:route>set-000L.xml</fr:route><fr:title
text="Cartesian product">Cartesian product</fr:title><fr:taxon>Proposition</fr:taxon><fr:date><fr:year>2024</fr:year><fr:month>10</fr:month><fr:day>20</fr:day></fr:date><fr:authors /></fr:frontmatter><fr:mainmatter><fr:p>Let <fr:tex
display="inline"><![CDATA[A,B]]></fr:tex> be sets.
  Then <fr:tex
display="inline"><![CDATA[A \times  B := {\mathopen {}\{(a,b)\colon a \in  A \wedge  b \in  B\}\mathclose {}}]]></fr:tex> is a set.</fr:p>
    
      
      <fr:tree
toc="false"
numbered="true"
show-heading="true"
show-metadata="false"
expanded="true"
root="false"
xmlns:fr="http://www.jonmsterling.com/jms-005P.xml"><fr:frontmatter><fr:anchor>353</fr:anchor><fr:addr
type="machine">#258</fr:addr><fr:route>unstable-258.xml</fr:route><fr:taxon>Proof</fr:taxon><fr:date><fr:year>2024</fr:year><fr:month>10</fr:month><fr:day>20</fr:day></fr:date><fr:authors /></fr:frontmatter><fr:mainmatter>
  Let <fr:tex
display="inline"><![CDATA[a \in  A, b \in  B]]></fr:tex>.
  By <fr:link
type="local"
href="set-000I.xml"
addr="set-000I"
title="Ordered pairs">definition</fr:link>, <fr:tex
display="inline"><![CDATA[(a,b) = {\mathopen {}\{{\mathopen {}\{a\}\mathclose {}},{\mathopen {}\{a,b\}\mathclose {}}\}\mathclose {}}]]></fr:tex>.
  Thus, by the <fr:link
type="local"
href="set-0006.xml"
addr="set-0006"
title="Axiom of powerset">powerset axiom</fr:link>, <fr:tex
display="inline"><![CDATA[(a,b) \in  \mathcal {P}(\mathcal {P}(A \cup  B))]]></fr:tex>.
  By <fr:link
type="local"
href="set-0005.xml"
addr="set-0005"
title="Axiom schema of separation">separation</fr:link>,
  <fr:tex
display="block"><![CDATA[     A \times  B = {\mathopen {}\{p \in  \mathcal {P}(\mathcal {P}(A \cup  B))\colon \exists a.\mkern 5mu\exists b.\mkern 5mup = (a,b)\}\mathclose {}}   ]]></fr:tex>
  is a set.
</fr:mainmatter><fr:backmatter /></fr:tree>
    
  </fr:mainmatter><fr:backmatter /></fr:tree></fr:mainmatter><fr:backmatter /></fr:tree>

  <fr:tree
toc="true"
numbered="true"
show-heading="true"
show-metadata="false"
expanded="true"
root="false"
xmlns:fr="http://www.jonmsterling.com/jms-005P.xml"><fr:frontmatter><fr:anchor>354</fr:anchor><fr:addr
type="machine">#268</fr:addr><fr:route>unstable-268.xml</fr:route><fr:title
text="Relations and functions">Relations and functions</fr:title><fr:date><fr:year>2024</fr:year><fr:month>10</fr:month><fr:day>20</fr:day></fr:date><fr:authors /></fr:frontmatter><fr:mainmatter><fr:tree
toc="true"
numbered="true"
show-heading="true"
show-metadata="false"
expanded="true"
root="false"
xmlns:fr="http://www.jonmsterling.com/jms-005P.xml"><fr:frontmatter><fr:anchor>355</fr:anchor><fr:addr
type="user">set-000M</fr:addr><fr:route>set-000M.xml</fr:route><fr:title
text="Relation">Relation</fr:title><fr:taxon>Definition</fr:taxon><fr:date><fr:year>2024</fr:year><fr:month>10</fr:month><fr:day>20</fr:day></fr:date><fr:authors /></fr:frontmatter><fr:mainmatter><fr:p>A <fr:em><fr:strong>(binary) relation</fr:strong></fr:em> <fr:tex
display="inline"><![CDATA[R\colon A\nrightarrow B]]></fr:tex> is a subset <fr:tex
display="inline"><![CDATA[R \subseteq  A \times  B]]></fr:tex>.
  Its <fr:em><fr:strong>support</fr:strong></fr:em> is the set <fr:tex
display="inline"><![CDATA[\mathsf {supp}(R) := {\mathopen {}\{a \in  A\colon \exists b \in  B.\mkern 5mu(a,b) \in  R\}\mathclose {}}]]></fr:tex> and its <fr:em><fr:strong>range</fr:strong></fr:em> is the set <fr:tex
display="inline"><![CDATA[\mathsf {ran}(R) := {\mathopen {}\{b \in  B\colon \exists a \in  A.\mkern 5mu(a,b) \in  R\}\mathclose {}}]]></fr:tex>.</fr:p></fr:mainmatter><fr:backmatter /></fr:tree><fr:tree
toc="true"
numbered="true"
show-heading="true"
show-metadata="false"
expanded="true"
root="false"
xmlns:fr="http://www.jonmsterling.com/jms-005P.xml"><fr:frontmatter><fr:anchor>356</fr:anchor><fr:addr
type="user">set-000N</fr:addr><fr:route>set-000N.xml</fr:route><fr:title
text="Total relation">Total <fr:link
type="local"
href="set-000M.xml"
addr="set-000M"
title="Relation">relation</fr:link></fr:title><fr:taxon>Definition</fr:taxon><fr:date><fr:year>2024</fr:year><fr:month>10</fr:month><fr:day>20</fr:day></fr:date><fr:authors /></fr:frontmatter><fr:mainmatter><fr:p>A relation <fr:tex
display="inline"><![CDATA[R\colon A\nrightarrow B]]></fr:tex> is <fr:em><fr:strong>total</fr:strong></fr:em> if <fr:tex
display="inline"><![CDATA[\mathsf {supp}(R) = A]]></fr:tex>.
  In other words, for all <fr:tex
display="inline"><![CDATA[a \in  A]]></fr:tex> there exists <fr:tex
display="inline"><![CDATA[b \in  B]]></fr:tex> such that <fr:tex
display="inline"><![CDATA[(a,b) \in  R]]></fr:tex>.</fr:p></fr:mainmatter><fr:backmatter /></fr:tree><fr:tree
toc="true"
numbered="true"
show-heading="true"
show-metadata="false"
expanded="true"
root="false"
xmlns:fr="http://www.jonmsterling.com/jms-005P.xml"><fr:frontmatter><fr:anchor>357</fr:anchor><fr:addr
type="user">set-000O</fr:addr><fr:route>set-000O.xml</fr:route><fr:title
text="Functional relation">Functional <fr:link
type="local"
href="set-000M.xml"
addr="set-000M"
title="Relation">relation</fr:link></fr:title><fr:taxon>Definition</fr:taxon><fr:date><fr:year>2024</fr:year><fr:month>10</fr:month><fr:day>20</fr:day></fr:date><fr:authors /></fr:frontmatter><fr:mainmatter><fr:p>A relation <fr:tex
display="inline"><![CDATA[R\colon A\nrightarrow B]]></fr:tex> is <fr:em><fr:strong>functional</fr:strong></fr:em> if for any <fr:tex
display="inline"><![CDATA[(a,b),(c,d) \in  R]]></fr:tex> if <fr:tex
display="inline"><![CDATA[a = c]]></fr:tex> then <fr:tex
display="inline"><![CDATA[b = d]]></fr:tex>.</fr:p></fr:mainmatter><fr:backmatter /></fr:tree><fr:tree
toc="true"
numbered="true"
show-heading="true"
show-metadata="false"
expanded="true"
root="false"
xmlns:fr="http://www.jonmsterling.com/jms-005P.xml"><fr:frontmatter><fr:anchor>358</fr:anchor><fr:addr
type="user">set-000P</fr:addr><fr:route>set-000P.xml</fr:route><fr:title
text="Injective relation">Injective <fr:link
type="local"
href="set-000M.xml"
addr="set-000M"
title="Relation">relation</fr:link></fr:title><fr:taxon>Definition</fr:taxon><fr:date><fr:year>2024</fr:year><fr:month>10</fr:month><fr:day>20</fr:day></fr:date><fr:authors /></fr:frontmatter><fr:mainmatter><fr:p>A relation <fr:tex
display="inline"><![CDATA[R\colon A\nrightarrow B]]></fr:tex> is <fr:em><fr:strong>injective</fr:strong></fr:em> if for every <fr:tex
display="inline"><![CDATA[(a,b),(c,d) \in  R]]></fr:tex> if <fr:tex
display="inline"><![CDATA[b = d]]></fr:tex> then <fr:tex
display="inline"><![CDATA[a = c]]></fr:tex>.</fr:p></fr:mainmatter><fr:backmatter /></fr:tree><fr:tree
toc="true"
numbered="true"
show-heading="true"
show-metadata="false"
expanded="true"
root="false"
xmlns:fr="http://www.jonmsterling.com/jms-005P.xml"><fr:frontmatter><fr:anchor>359</fr:anchor><fr:addr
type="user">set-000Q</fr:addr><fr:route>set-000Q.xml</fr:route><fr:title
text="Surjective relation">Surjective <fr:link
type="local"
href="set-000M.xml"
addr="set-000M"
title="Relation">relation</fr:link></fr:title><fr:taxon>Definition</fr:taxon><fr:date><fr:year>2024</fr:year><fr:month>10</fr:month><fr:day>20</fr:day></fr:date><fr:authors /></fr:frontmatter><fr:mainmatter><fr:p>A relation <fr:tex
display="inline"><![CDATA[R\colon A\nrightarrow B]]></fr:tex> is <fr:em><fr:strong>surjective</fr:strong></fr:em> if <fr:tex
display="inline"><![CDATA[\mathsf {ran}(R) = B]]></fr:tex>.
  In other words, for every <fr:tex
display="inline"><![CDATA[b \in  B]]></fr:tex> there is <fr:tex
display="inline"><![CDATA[a \in  A]]></fr:tex> such that <fr:tex
display="inline"><![CDATA[(a,b) \in  R]]></fr:tex>.</fr:p></fr:mainmatter><fr:backmatter /></fr:tree><fr:tree
toc="true"
numbered="true"
show-heading="true"
show-metadata="false"
expanded="true"
root="false"
xmlns:fr="http://www.jonmsterling.com/jms-005P.xml"><fr:frontmatter><fr:anchor>360</fr:anchor><fr:addr
type="user">set-000R</fr:addr><fr:route>set-000R.xml</fr:route><fr:title
text="Function">Function</fr:title><fr:taxon>Definition</fr:taxon><fr:date><fr:year>2024</fr:year><fr:month>10</fr:month><fr:day>20</fr:day></fr:date><fr:authors /></fr:frontmatter><fr:mainmatter><fr:p>A <fr:em><fr:strong>function</fr:strong></fr:em> <fr:tex
display="inline"><![CDATA[f\colon A\to B]]></fr:tex> is a <fr:link
type="local"
href="set-000N.xml"
addr="set-000N"
title="Total relation">total</fr:link> and <fr:link
type="local"
href="set-000O.xml"
addr="set-000O"
title="Functional relation">functional</fr:link> <fr:link
type="local"
href="set-000M.xml"
addr="set-000M"
title="Relation">relation</fr:link> <fr:tex
display="inline"><![CDATA[f\colon A\nrightarrow B]]></fr:tex>.
  We define <fr:tex
display="inline"><![CDATA[B^{A} := {\mathopen {}\{f \in  \mathcal {P}(A \times  B)\colon \text {$f$ is a function}\}\mathclose {}}]]></fr:tex>.</fr:p></fr:mainmatter><fr:backmatter /></fr:tree><fr:tree
toc="true"
numbered="true"
show-heading="true"
show-metadata="false"
expanded="true"
root="false"
xmlns:fr="http://www.jonmsterling.com/jms-005P.xml"><fr:frontmatter><fr:anchor>361</fr:anchor><fr:addr
type="user">set-000S</fr:addr><fr:route>set-000S.xml</fr:route><fr:title
text="Functional extensionality">Functional extensionality</fr:title><fr:taxon>Proposition</fr:taxon><fr:date><fr:year>2024</fr:year><fr:month>10</fr:month><fr:day>20</fr:day></fr:date><fr:authors /></fr:frontmatter><fr:mainmatter><fr:p>Let <fr:tex
display="inline"><![CDATA[f,g\colon A\to B]]></fr:tex> be <fr:link
type="local"
href="set-000R.xml"
addr="set-000R"
title="Function">functions</fr:link>.
  Then <fr:tex
display="inline"><![CDATA[f = g]]></fr:tex> if and only if for all <fr:tex
display="inline"><![CDATA[a \in  A]]></fr:tex>, <fr:tex
display="inline"><![CDATA[f(a) = g(a)]]></fr:tex>.</fr:p>
    
      
      <fr:tree
toc="false"
numbered="true"
show-heading="true"
show-metadata="false"
expanded="true"
root="false"
xmlns:fr="http://www.jonmsterling.com/jms-005P.xml"><fr:frontmatter><fr:anchor>362</fr:anchor><fr:addr
type="machine">#257</fr:addr><fr:route>unstable-257.xml</fr:route><fr:taxon>Proof</fr:taxon><fr:date><fr:year>2024</fr:year><fr:month>10</fr:month><fr:day>20</fr:day></fr:date><fr:authors /></fr:frontmatter><fr:mainmatter>
  The if direction is trivial.
  For the only if direction, assume that <fr:tex
display="inline"><![CDATA[f(a) = g(a)]]></fr:tex> for all <fr:tex
display="inline"><![CDATA[a \in  A]]></fr:tex>.
  By <fr:link
type="local"
href="set-0001.xml"
addr="set-0001"
title="Axiom of extensionality">extensionality</fr:link>, it suffices to show that for any <fr:tex
display="inline"><![CDATA[(a,b) \in  A \times  B]]></fr:tex>, <fr:tex
display="inline"><![CDATA[(a,b) \in  f]]></fr:tex> if and only if <fr:tex
display="inline"><![CDATA[(a,b) \in  g]]></fr:tex>.
  Suppose that <fr:tex
display="inline"><![CDATA[(a,b) \in  f]]></fr:tex>, then by <fr:link
type="local"
href="set-000O.xml"
addr="set-000O"
title="Functional relation">functionality</fr:link>, <fr:tex
display="inline"><![CDATA[b = f(a)]]></fr:tex>.
  By <fr:link
type="local"
href="set-000N.xml"
addr="set-000N"
title="Total relation">totality</fr:link>, <fr:tex
display="inline"><![CDATA[(a,g(a)) \in  g]]></fr:tex>.
  By hypothesis, <fr:tex
display="inline"><![CDATA[(a,f(a)) = (a,g(a))]]></fr:tex>.
  Thus, <fr:tex
display="inline"><![CDATA[(a,f(a)) \in  g]]></fr:tex>.
  The converse is analogous.
</fr:mainmatter><fr:backmatter /></fr:tree>
    
  </fr:mainmatter><fr:backmatter /></fr:tree><fr:tree
toc="true"
numbered="true"
show-heading="true"
show-metadata="false"
expanded="true"
root="false"
xmlns:fr="http://www.jonmsterling.com/jms-005P.xml"><fr:frontmatter><fr:anchor>363</fr:anchor><fr:addr
type="user">set-0015</fr:addr><fr:route>set-0015.xml</fr:route><fr:title
text="External functions can be internalized">External functions can be internalized</fr:title><fr:taxon>Proposition</fr:taxon><fr:date><fr:year>2024</fr:year><fr:month>10</fr:month><fr:day>21</fr:day></fr:date><fr:authors /></fr:frontmatter><fr:mainmatter><fr:p>Let <fr:tex
display="inline"><![CDATA[\varphi ]]></fr:tex> be a formula with at most <fr:tex
display="inline"><![CDATA[x,y]]></fr:tex> free such that the following two conditions hold:
  <fr:ul><fr:li><fr:tex
display="inline"><![CDATA[\forall a.\mkern 5mu\exists b.\mkern 5mu\varphi (a,b)]]></fr:tex>;</fr:li>
    <fr:li><fr:tex
display="inline"><![CDATA[\forall a,b,b'.\mkern 5mu\varphi (a,b) \wedge  \varphi (a,b') \Rightarrow  b = b']]></fr:tex>.</fr:li></fr:ul>
  Then for any set <fr:tex
display="inline"><![CDATA[A]]></fr:tex>, there is a function <fr:tex
display="inline"><![CDATA[f]]></fr:tex> with <fr:tex
display="inline"><![CDATA[\mathsf {dom}(f) = A]]></fr:tex> such that
  <fr:tex
display="block"><![CDATA[     f(a) = b \Leftrightarrow  \varphi (a,b).   ]]></fr:tex></fr:p>
    
      
      <fr:tree
toc="false"
numbered="true"
show-heading="true"
show-metadata="false"
expanded="true"
root="false"
xmlns:fr="http://www.jonmsterling.com/jms-005P.xml"><fr:frontmatter><fr:anchor>364</fr:anchor><fr:addr
type="machine">#247</fr:addr><fr:route>unstable-247.xml</fr:route><fr:taxon>Proof</fr:taxon><fr:date><fr:year>2024</fr:year><fr:month>10</fr:month><fr:day>21</fr:day></fr:date><fr:authors /></fr:frontmatter><fr:mainmatter>
  By <fr:link
type="local"
href="set-0008.xml"
addr="set-0008"
title="Axiom schema of replacement">replacement</fr:link>, <fr:tex
display="inline"><![CDATA[\mathsf {ran}(\varphi ) := {\mathopen {}\{y\colon \exists x \in  A.\mkern 5mu\varphi (x,y)\}\mathclose {}}]]></fr:tex> is a set.
  Then we define <fr:tex
display="inline"><![CDATA[f\colon A\to \mathsf {ran}(\varphi )]]></fr:tex> by
  <fr:tex
display="block"><![CDATA[     (a,b) \in  f \Leftrightarrow  \varphi (a,b).   ]]></fr:tex>
  The requirements placed on <fr:tex
display="inline"><![CDATA[\varphi ]]></fr:tex> guarantee that <fr:tex
display="inline"><![CDATA[f]]></fr:tex> is a function.
</fr:mainmatter><fr:backmatter /></fr:tree>
    
  </fr:mainmatter><fr:backmatter /></fr:tree><fr:tree
toc="true"
numbered="true"
show-heading="true"
show-metadata="false"
expanded="true"
root="false"
xmlns:fr="http://www.jonmsterling.com/jms-005P.xml"><fr:frontmatter><fr:anchor>365</fr:anchor><fr:addr
type="user">set-0016</fr:addr><fr:route>set-0016.xml</fr:route><fr:title
text="Every function can be externalized">Every function can be externalized</fr:title><fr:taxon>Proposition</fr:taxon><fr:date><fr:year>2024</fr:year><fr:month>10</fr:month><fr:day>21</fr:day></fr:date><fr:authors /></fr:frontmatter><fr:mainmatter><fr:p>Let <fr:tex
display="inline"><![CDATA[f\colon A\to B]]></fr:tex> be a function.
  Then there is a definable mapping <fr:tex
display="inline"><![CDATA[\varphi ]]></fr:tex> with <fr:tex
display="inline"><![CDATA[x,y]]></fr:tex> free such that for any <fr:tex
display="inline"><![CDATA[a \in  A]]></fr:tex> and <fr:tex
display="inline"><![CDATA[b \in  B]]></fr:tex>,
  <fr:tex
display="block"><![CDATA[     f(a) = b \Leftrightarrow  \varphi (a,b).   ]]></fr:tex></fr:p>
    
      
      <fr:tree
toc="false"
numbered="true"
show-heading="true"
show-metadata="false"
expanded="true"
root="false"
xmlns:fr="http://www.jonmsterling.com/jms-005P.xml"><fr:frontmatter><fr:anchor>366</fr:anchor><fr:addr
type="machine">#246</fr:addr><fr:route>unstable-246.xml</fr:route><fr:taxon>Proof</fr:taxon><fr:date><fr:year>2024</fr:year><fr:month>10</fr:month><fr:day>21</fr:day></fr:date><fr:authors /></fr:frontmatter><fr:mainmatter>
  Define
  <fr:tex
display="block"><![CDATA[     \varphi  := (a \in  A \Rightarrow  \exists b \in  B.\mkern 5mu(a,b) \in  f) \wedge  (a \notin  A \Rightarrow  y = \varnothing ).   ]]></fr:tex>
  The fact that <fr:tex
display="inline"><![CDATA[f]]></fr:tex> is a function makes <fr:tex
display="inline"><![CDATA[\varphi ]]></fr:tex> a definable mapping.
  The required condition is easy to verify.
</fr:mainmatter><fr:backmatter /></fr:tree>
    
  </fr:mainmatter><fr:backmatter /></fr:tree></fr:mainmatter><fr:backmatter /></fr:tree>

  <fr:tree
toc="true"
numbered="true"
show-heading="true"
show-metadata="false"
expanded="true"
root="false"
xmlns:fr="http://www.jonmsterling.com/jms-005P.xml"><fr:frontmatter><fr:anchor>367</fr:anchor><fr:addr
type="machine">#269</fr:addr><fr:route>unstable-269.xml</fr:route><fr:title
text="Natural numbers">Natural numbers</fr:title><fr:date><fr:year>2024</fr:year><fr:month>10</fr:month><fr:day>20</fr:day></fr:date><fr:authors /></fr:frontmatter><fr:mainmatter><fr:tree
toc="true"
numbered="true"
show-heading="true"
show-metadata="false"
expanded="true"
root="false"
xmlns:fr="http://www.jonmsterling.com/jms-005P.xml"><fr:frontmatter><fr:anchor>368</fr:anchor><fr:addr
type="user">set-000T</fr:addr><fr:route>set-000T.xml</fr:route><fr:title
text="Natural number set">Natural number set</fr:title><fr:taxon>Definition</fr:taxon><fr:date><fr:year>2024</fr:year><fr:month>10</fr:month><fr:day>20</fr:day></fr:date><fr:authors /></fr:frontmatter><fr:mainmatter><fr:p>A set <fr:tex
display="inline"><![CDATA[N]]></fr:tex> is called a <fr:em><fr:strong>natural number set</fr:strong></fr:em> if it is equipped with
  <fr:ul><fr:li>an element <fr:tex
display="inline"><![CDATA[0 \in  N]]></fr:tex>;</fr:li>
    <fr:li>a successor <fr:link
type="local"
href="set-000R.xml"
addr="set-000R"
title="Function">function</fr:link> <fr:tex
display="inline"><![CDATA[s\colon N\to N]]></fr:tex>.</fr:li></fr:ul>
  These data are subject to the following requirements.
  <fr:ul><fr:li><fr:tex
display="inline"><![CDATA[s\colon N\to N]]></fr:tex> is <fr:link
type="local"
href="set-000P.xml"
addr="set-000P"
title="Injective relation">injective</fr:link>;</fr:li>
    <fr:li>non-looping: for every <fr:tex
display="inline"><![CDATA[x \in  N]]></fr:tex>, <fr:tex
display="inline"><![CDATA[s(x) \neq  0]]></fr:tex>;</fr:li>
    <fr:li>induction principle: for every set <fr:tex
display="inline"><![CDATA[P \subseteq  N]]></fr:tex>, if <fr:tex
display="inline"><![CDATA[0 \in  P]]></fr:tex> and for all <fr:tex
display="inline"><![CDATA[x \in  N]]></fr:tex>, <fr:tex
display="inline"><![CDATA[x \in  P]]></fr:tex> implies that <fr:tex
display="inline"><![CDATA[s(x) \in  P]]></fr:tex> then <fr:tex
display="inline"><![CDATA[P = N]]></fr:tex>.</fr:li></fr:ul></fr:p></fr:mainmatter><fr:backmatter /></fr:tree><fr:tree
toc="true"
numbered="true"
show-heading="true"
show-metadata="false"
expanded="true"
root="false"
xmlns:fr="http://www.jonmsterling.com/jms-005P.xml"><fr:frontmatter><fr:anchor>369</fr:anchor><fr:addr
type="user">set-000U</fr:addr><fr:route>set-000U.xml</fr:route><fr:title
text="Successor inequality">Successor inequality</fr:title><fr:taxon>Proposition</fr:taxon><fr:date><fr:year>2024</fr:year><fr:month>10</fr:month><fr:day>20</fr:day></fr:date><fr:authors /></fr:frontmatter><fr:mainmatter><fr:p>Let <fr:tex
display="inline"><![CDATA[N]]></fr:tex> be a <fr:link
type="local"
href="set-000T.xml"
addr="set-000T"
title="Natural number set">natural number set</fr:link>.
  Then for any <fr:tex
display="inline"><![CDATA[n \in  N]]></fr:tex>, <fr:tex
display="inline"><![CDATA[s(n) \neq  n]]></fr:tex>.</fr:p>
    
      
      <fr:tree
toc="false"
numbered="true"
show-heading="true"
show-metadata="false"
expanded="true"
root="false"
xmlns:fr="http://www.jonmsterling.com/jms-005P.xml"><fr:frontmatter><fr:anchor>370</fr:anchor><fr:addr
type="machine">#256</fr:addr><fr:route>unstable-256.xml</fr:route><fr:taxon>Proof</fr:taxon><fr:date><fr:year>2024</fr:year><fr:month>10</fr:month><fr:day>20</fr:day></fr:date><fr:authors /></fr:frontmatter><fr:mainmatter>
  Consider the subset <fr:tex
display="inline"><![CDATA[P := {\mathopen {}\{x \in  N\colon s(x) \neq  x\}\mathclose {}}]]></fr:tex>.
  By the induction principle, it suffices to show that <fr:tex
display="inline"><![CDATA[0 \in  P]]></fr:tex> and for any <fr:tex
display="inline"><![CDATA[x \in  N]]></fr:tex>, if <fr:tex
display="inline"><![CDATA[x \in  P]]></fr:tex> then <fr:tex
display="inline"><![CDATA[s(x) \in  P]]></fr:tex>.
  First, <fr:tex
display="inline"><![CDATA[0 \in  P]]></fr:tex> follows from the non-looping property.
  Now assume that <fr:tex
display="inline"><![CDATA[x \in  P]]></fr:tex>, i.e., <fr:tex
display="inline"><![CDATA[s(x) \neq  x]]></fr:tex>.
  Then if <fr:tex
display="inline"><![CDATA[s(s(x)) = s(x)]]></fr:tex>, by injectivity, <fr:tex
display="inline"><![CDATA[s(x) = x]]></fr:tex>, which is a contradiction.
  Thus, <fr:tex
display="inline"><![CDATA[s(s(x)) \neq  s(x)]]></fr:tex>.
  In other words, <fr:tex
display="inline"><![CDATA[s(x) \in  P]]></fr:tex>.
</fr:mainmatter><fr:backmatter /></fr:tree>
    
  </fr:mainmatter><fr:backmatter /></fr:tree><fr:tree
toc="true"
numbered="true"
show-heading="true"
show-metadata="false"
expanded="true"
root="false"
xmlns:fr="http://www.jonmsterling.com/jms-005P.xml"><fr:frontmatter><fr:anchor>371</fr:anchor><fr:addr
type="user">set-000W</fr:addr><fr:route>set-000W.xml</fr:route><fr:title
text="Set membership respects successor">Set membership respects successor</fr:title><fr:taxon>Lemma</fr:taxon><fr:date><fr:year>2024</fr:year><fr:month>10</fr:month><fr:day>20</fr:day></fr:date><fr:authors /></fr:frontmatter><fr:mainmatter><fr:p>Let <fr:tex
display="inline"><![CDATA[N]]></fr:tex> be an inductive set admitting the induction principle defined in <fr:link
type="local"
href="set-000T.xml"
addr="set-000T"
title="Natural number set">natural number set</fr:link>.
  For each <fr:tex
display="inline"><![CDATA[n \in  N]]></fr:tex>, we define <fr:tex
display="inline"><![CDATA[s(n) := n \cup  {\mathopen {}\{n\}\mathclose {}}]]></fr:tex>.
  Then for any <fr:tex
display="inline"><![CDATA[m,n \in  N]]></fr:tex>, if <fr:tex
display="inline"><![CDATA[m \in  n]]></fr:tex> then <fr:tex
display="inline"><![CDATA[s(m) \in  s(n)]]></fr:tex>.</fr:p>
    
      
      <fr:tree
toc="false"
numbered="true"
show-heading="true"
show-metadata="false"
expanded="true"
root="false"
xmlns:fr="http://www.jonmsterling.com/jms-005P.xml"><fr:frontmatter><fr:anchor>372</fr:anchor><fr:addr
type="machine">#253</fr:addr><fr:route>unstable-253.xml</fr:route><fr:taxon>Proof</fr:taxon><fr:date><fr:year>2024</fr:year><fr:month>10</fr:month><fr:day>20</fr:day></fr:date><fr:authors /></fr:frontmatter><fr:mainmatter>
  <fr:p>Fix <fr:tex
display="inline"><![CDATA[m \in  N]]></fr:tex>.
    Consider <fr:tex
display="inline"><![CDATA[P := {\mathopen {}\{n \in  N\colon m \in  n \Rightarrow  s(m) \in  s(n)\}\mathclose {}}]]></fr:tex>.
    Note that <fr:tex
display="inline"><![CDATA[\varnothing  \in  P]]></fr:tex> vacuously.</fr:p>
  <fr:p>Now let <fr:tex
display="inline"><![CDATA[n \in  P]]></fr:tex>, i.e., <fr:tex
display="inline"><![CDATA[m \in  n \Rightarrow  s(m) \in  s(n)]]></fr:tex>.
    We need to show that <fr:tex
display="inline"><![CDATA[s(n) \in  P]]></fr:tex>, i.e., <fr:tex
display="inline"><![CDATA[m \in  s(n) \Rightarrow  s(m) \in  s(s(n))]]></fr:tex>.
    Suppose that <fr:tex
display="inline"><![CDATA[m \in  s(n) = n \cup  {\mathopen {}\{n\}\mathclose {}}]]></fr:tex>.
    By <fr:link
type="local"
href="set-0004.xml"
addr="set-0004"
title="Axiom of union">union</fr:link>, <fr:tex
display="inline"><![CDATA[m \in  n]]></fr:tex> or <fr:tex
display="inline"><![CDATA[m \in  {\mathopen {}\{n\}\mathclose {}}]]></fr:tex>.
    In the former case, we have <fr:tex
display="inline"><![CDATA[s(m) \in  s(n) \subseteq  s(n) \cup  {\mathopen {}\{s(n)\}\mathclose {}} = s(s(n))]]></fr:tex>.
    In the latter case, we have <fr:tex
display="inline"><![CDATA[m = n]]></fr:tex> by <fr:ref
addr="set-000H"
href="set-000H.xml"
taxon="Proposition" />.
    Then <fr:tex
display="inline"><![CDATA[s(m) = s(n) \in  s(n) \cup  {\mathopen {}\{s(n)\}\mathclose {}} = s(s(n))]]></fr:tex>.</fr:p>
</fr:mainmatter><fr:backmatter /></fr:tree>
    
  </fr:mainmatter><fr:backmatter /></fr:tree><fr:tree
toc="true"
numbered="true"
show-heading="true"
show-metadata="false"
expanded="true"
root="false"
xmlns:fr="http://www.jonmsterling.com/jms-005P.xml"><fr:frontmatter><fr:anchor>373</fr:anchor><fr:addr
type="user">set-000V</fr:addr><fr:route>set-000V.xml</fr:route><fr:title
text="Natural numbers">Natural numbers</fr:title><fr:taxon>Construction</fr:taxon><fr:date><fr:year>2024</fr:year><fr:month>10</fr:month><fr:day>20</fr:day></fr:date><fr:authors /></fr:frontmatter><fr:mainmatter><fr:p>Let <fr:tex
display="inline"><![CDATA[I]]></fr:tex> be the inductive set guaranteed by <fr:link
type="local"
href="set-0007.xml"
addr="set-0007"
title="Axiom of infinity">infinity</fr:link>.
  Define
  <fr:tex
display="block"><![CDATA[     \mathbb {N} := \bigcap {\mathopen {}\{S \in  \mathcal {P}(I)\colon \text {$S$ is inductive}\}\mathclose {}}.   ]]></fr:tex>
  For this construction to work, we must show that <fr:tex
display="inline"><![CDATA[\mathbb {N}]]></fr:tex> is inductive.</fr:p>
    
      
      <fr:tree
toc="false"
numbered="true"
show-heading="true"
show-metadata="false"
expanded="true"
root="false"
xmlns:fr="http://www.jonmsterling.com/jms-005P.xml"><fr:frontmatter><fr:anchor>374</fr:anchor><fr:addr
type="machine">#254</fr:addr><fr:route>unstable-254.xml</fr:route><fr:taxon>Proof</fr:taxon><fr:date><fr:year>2024</fr:year><fr:month>10</fr:month><fr:day>20</fr:day></fr:date><fr:authors /></fr:frontmatter><fr:mainmatter>
  By definition, every inductive set <fr:tex
display="inline"><![CDATA[S]]></fr:tex> contains <fr:tex
display="inline"><![CDATA[\varnothing ]]></fr:tex>.
  Thus, it follows that <fr:tex
display="inline"><![CDATA[\varnothing  \in  \mathbb {N}]]></fr:tex>.
  Now for any <fr:tex
display="inline"><![CDATA[x \in  \mathbb {N}]]></fr:tex>, we have <fr:tex
display="inline"><![CDATA[x \in  S]]></fr:tex> for any inductive set <fr:tex
display="inline"><![CDATA[S \subseteq  I]]></fr:tex>.
  Thus, <fr:tex
display="inline"><![CDATA[x \cup  {\mathopen {}\{x\}\mathclose {}}]]></fr:tex> is an element of every inductive subset of <fr:tex
display="inline"><![CDATA[I]]></fr:tex>.
  Then it follows that <fr:tex
display="inline"><![CDATA[x \cup  {\mathopen {}\{x\}\mathclose {}} \in  \mathbb {N}]]></fr:tex>.
</fr:mainmatter><fr:backmatter /></fr:tree>
    
  <fr:p>We take <fr:tex
display="inline"><![CDATA[0 := \varnothing  \in  \mathbb {N}]]></fr:tex> and we define <fr:tex
display="inline"><![CDATA[s\colon \mathbb {N}\to \mathbb {N}]]></fr:tex> by <fr:tex
display="inline"><![CDATA[s(x) = x \cup  {\mathopen {}\{x\}\mathclose {}}]]></fr:tex>.
  It remains to show that <fr:tex
display="inline"><![CDATA[\mathbb {N}]]></fr:tex> is a <fr:link
type="local"
href="set-000T.xml"
addr="set-000T"
title="Natural number set">natural number set</fr:link>.</fr:p>
    
      
      <fr:tree
toc="false"
numbered="true"
show-heading="true"
show-metadata="false"
expanded="true"
root="false"
xmlns:fr="http://www.jonmsterling.com/jms-005P.xml"><fr:frontmatter><fr:anchor>375</fr:anchor><fr:addr
type="machine">#255</fr:addr><fr:route>unstable-255.xml</fr:route><fr:taxon>Proof</fr:taxon><fr:date><fr:year>2024</fr:year><fr:month>10</fr:month><fr:day>20</fr:day></fr:date><fr:authors /></fr:frontmatter><fr:mainmatter>
  <fr:p>First, we prove the non-looping property.
    Observe that <fr:tex
display="inline"><![CDATA[s(\varnothing ) = \varnothing  \cup  {\mathopen {}\{\varnothing \}\mathclose {}} = {\mathopen {}\{\varnothing \}\mathclose {}} \neq  \varnothing ]]></fr:tex>.</fr:p>
  <fr:p>To show the induction principle, let <fr:tex
display="inline"><![CDATA[P \subseteq  \mathbb {N}]]></fr:tex> such that <fr:tex
display="inline"><![CDATA[0 \in  P]]></fr:tex> and for any <fr:tex
display="inline"><![CDATA[x \in  \mathbb {N}]]></fr:tex>, <fr:tex
display="inline"><![CDATA[x \in  P]]></fr:tex> implies that <fr:tex
display="inline"><![CDATA[s(x) \in  P]]></fr:tex>.
    Note that the hypothesis implies that <fr:tex
display="inline"><![CDATA[P]]></fr:tex> is inductive.
    Thus, <fr:tex
display="inline"><![CDATA[\mathbb {N} \subseteq  P]]></fr:tex> by construction.
    Then by <fr:link
type="local"
href="set-0001.xml"
addr="set-0001"
title="Axiom of extensionality">extensionality</fr:link>, <fr:tex
display="inline"><![CDATA[\mathbb {N} = P]]></fr:tex>.</fr:p>
  <fr:p>It remains to show that <fr:tex
display="inline"><![CDATA[s]]></fr:tex> is <fr:link
type="local"
href="set-000P.xml"
addr="set-000P"
title="Injective relation">injective</fr:link>.
    Let <fr:tex
display="inline"><![CDATA[n,m \in  \mathbb {N}]]></fr:tex>.
    Suppose that <fr:tex
display="inline"><![CDATA[s(n) = s(m)]]></fr:tex>.
    Then by definition <fr:tex
display="inline"><![CDATA[n \cup  {\mathopen {}\{n\}\mathclose {}} = m \cup  {\mathopen {}\{m\}\mathclose {}}]]></fr:tex>.
    Since <fr:tex
display="inline"><![CDATA[n \in  n \cup  {\mathopen {}\{n\}\mathclose {}}]]></fr:tex>, <fr:tex
display="inline"><![CDATA[n \in  m \cup  {\mathopen {}\{m\}\mathclose {}}]]></fr:tex>.
    By <fr:link
type="local"
href="set-0004.xml"
addr="set-0004"
title="Axiom of union">union</fr:link>, <fr:tex
display="inline"><![CDATA[n \in  {\mathopen {}\{m\}\mathclose {}}]]></fr:tex> or <fr:tex
display="inline"><![CDATA[n \in  m]]></fr:tex>.
    In the former case, <fr:tex
display="inline"><![CDATA[n = m]]></fr:tex> by <fr:ref
addr="set-000H"
href="set-000H.xml"
taxon="Proposition" />.
    In the latter case, we have <fr:tex
display="inline"><![CDATA[s(n) \in  s(m)]]></fr:tex> by <fr:ref
addr="set-000W"
href="set-000W.xml"
taxon="Lemma" />.
    But this means that we have <fr:tex
display="inline"><![CDATA[s(n) \in  s(m) = s(n)]]></fr:tex>, which contradicts <fr:ref
addr="set-000X"
href="set-000X.xml"
taxon="Proposition" />.</fr:p>
</fr:mainmatter><fr:backmatter /></fr:tree>
    
  </fr:mainmatter><fr:backmatter /></fr:tree></fr:mainmatter><fr:backmatter /></fr:tree>

  <fr:tree
toc="true"
numbered="true"
show-heading="true"
show-metadata="false"
expanded="true"
root="false"
xmlns:fr="http://www.jonmsterling.com/jms-005P.xml"><fr:frontmatter><fr:anchor>376</fr:anchor><fr:addr
type="machine">#270</fr:addr><fr:route>unstable-270.xml</fr:route><fr:title
text="Well orders">Well orders</fr:title><fr:date><fr:year>2024</fr:year><fr:month>10</fr:month><fr:day>20</fr:day></fr:date><fr:authors /></fr:frontmatter><fr:mainmatter><fr:tree
toc="true"
numbered="true"
show-heading="true"
show-metadata="false"
expanded="true"
root="false"
xmlns:fr="http://www.jonmsterling.com/jms-005P.xml"><fr:frontmatter><fr:anchor>377</fr:anchor><fr:addr
type="user">set-000Y</fr:addr><fr:route>set-000Y.xml</fr:route><fr:title
text="Well orders">Well orders</fr:title><fr:taxon>Definition</fr:taxon><fr:date><fr:year>2024</fr:year><fr:month>10</fr:month><fr:day>21</fr:day></fr:date><fr:authors /></fr:frontmatter><fr:mainmatter><fr:p>A set <fr:tex
display="inline"><![CDATA[X]]></fr:tex> is <fr:em><fr:strong>well-ordered</fr:strong></fr:em> by a linear order <fr:tex
display="inline"><![CDATA[\preceq  \subseteq  X \times  X]]></fr:tex> if every non-empty subset of <fr:tex
display="inline"><![CDATA[X]]></fr:tex> has a <fr:tex
display="inline"><![CDATA[\preceq ]]></fr:tex>-least element.</fr:p></fr:mainmatter><fr:backmatter /></fr:tree><fr:tree
toc="true"
numbered="true"
show-heading="true"
show-metadata="false"
expanded="true"
root="false"
xmlns:fr="http://www.jonmsterling.com/jms-005P.xml"><fr:frontmatter><fr:anchor>378</fr:anchor><fr:addr
type="user">set-000Z</fr:addr><fr:route>set-000Z.xml</fr:route><fr:title
text="Natural numbers are well ordered"><fr:link
type="local"
href="set-000V.xml"
addr="set-000V"
title="Natural numbers">Natural numbers</fr:link> are <fr:link
type="local"
href="set-000Y.xml"
addr="set-000Y"
title="Well orders">well ordered</fr:link></fr:title><fr:taxon>Proposition</fr:taxon><fr:date><fr:year>2024</fr:year><fr:month>10</fr:month><fr:day>21</fr:day></fr:date><fr:authors /></fr:frontmatter><fr:mainmatter><fr:p>The relation <fr:tex
display="inline"><![CDATA[\leq ]]></fr:tex> defined by <fr:tex
display="inline"><![CDATA[a \leq  b \Leftrightarrow  a \in  s(b)]]></fr:tex> is a well order on <fr:tex
display="inline"><![CDATA[\mathbb {N}]]></fr:tex>.</fr:p>
    
      
      <fr:tree
toc="false"
numbered="true"
show-heading="true"
show-metadata="false"
expanded="true"
root="false"
xmlns:fr="http://www.jonmsterling.com/jms-005P.xml"><fr:frontmatter><fr:anchor>325</fr:anchor><fr:addr
type="machine">#251</fr:addr><fr:route>unstable-251.xml</fr:route><fr:taxon>Proof</fr:taxon><fr:date><fr:year>2024</fr:year><fr:month>10</fr:month><fr:day>21</fr:day></fr:date><fr:authors /></fr:frontmatter><fr:mainmatter>
  <fr:p>By induction, one can show that <fr:tex
display="inline"><![CDATA[\leq ]]></fr:tex> is reflexive, transitive, and linear.
    It remains to show that <fr:tex
display="inline"><![CDATA[\leq ]]></fr:tex> is a well order.
    To this end, let <fr:tex
display="inline"><![CDATA[X \subseteq  \mathbb {N}]]></fr:tex> be a non-empty subset.
    Assume that <fr:tex
display="inline"><![CDATA[X]]></fr:tex> has no least elements.
    Consider <fr:tex
display="inline"><![CDATA[P := {\mathopen {}\{x \in  \mathbb {N}\colon \forall m \leq  x.\mkern 5mum \notin  X\}\mathclose {}}]]></fr:tex>.
    Note that <fr:tex
display="inline"><![CDATA[\varnothing  \notin  X]]></fr:tex> since it would be a least element of <fr:tex
display="inline"><![CDATA[X]]></fr:tex>.
    Hence, <fr:tex
display="inline"><![CDATA[0 \in  P]]></fr:tex>.</fr:p>
  <fr:p>Now, suppose that <fr:tex
display="inline"><![CDATA[x \in  P]]></fr:tex>, i.e., <fr:tex
display="inline"><![CDATA[\forall m \leq  x.\mkern 5mum \notin  X]]></fr:tex>.
    We need to show that <fr:tex
display="inline"><![CDATA[s(x) \in  P]]></fr:tex>, i.e., <fr:tex
display="inline"><![CDATA[\forall m \leq  s(x).\mkern 5mum \notin  X]]></fr:tex>.
    Let <fr:tex
display="inline"><![CDATA[m \leq  s(x)]]></fr:tex>.
    By definition, we have <fr:tex
display="inline"><![CDATA[m \in  s(x)]]></fr:tex> or <fr:tex
display="inline"><![CDATA[m = s(x)]]></fr:tex>.
    The latter case can be ruled out since it would be the least element of <fr:tex
display="inline"><![CDATA[X]]></fr:tex>.
    In the former case, we have <fr:tex
display="inline"><![CDATA[m \leq  x]]></fr:tex>.
    Thus, <fr:tex
display="inline"><![CDATA[m \notin  X]]></fr:tex> follows from the hypothesis.</fr:p>
  <fr:p>Since <fr:tex
display="inline"><![CDATA[P = \mathbb {N}]]></fr:tex>, this shows that <fr:tex
display="inline"><![CDATA[X = \varnothing ]]></fr:tex>, which contradicts the assumption that <fr:tex
display="inline"><![CDATA[X]]></fr:tex> is a non-empty set.</fr:p>
</fr:mainmatter><fr:backmatter /></fr:tree>
    
  </fr:mainmatter><fr:backmatter /></fr:tree></fr:mainmatter><fr:backmatter /></fr:tree>

  <fr:tree
toc="true"
numbered="true"
show-heading="true"
show-metadata="false"
expanded="true"
root="false"
xmlns:fr="http://www.jonmsterling.com/jms-005P.xml"><fr:frontmatter><fr:anchor>379</fr:anchor><fr:addr
type="machine">#271</fr:addr><fr:route>unstable-271.xml</fr:route><fr:title
text="Recursion">Recursion</fr:title><fr:date><fr:year>2024</fr:year><fr:month>10</fr:month><fr:day>20</fr:day></fr:date><fr:authors /></fr:frontmatter><fr:mainmatter><fr:tree
toc="true"
numbered="true"
show-heading="true"
show-metadata="false"
expanded="true"
root="false"
xmlns:fr="http://www.jonmsterling.com/jms-005P.xml"><fr:frontmatter><fr:anchor>380</fr:anchor><fr:addr
type="user">set-0010</fr:addr><fr:route>set-0010.xml</fr:route><fr:title
text="Germs">Germs</fr:title><fr:taxon>Definition</fr:taxon><fr:date><fr:year>2024</fr:year><fr:month>10</fr:month><fr:day>21</fr:day></fr:date><fr:authors /></fr:frontmatter><fr:mainmatter><fr:p>Let <fr:tex
display="inline"><![CDATA[X]]></fr:tex> be a set, <fr:tex
display="inline"><![CDATA[x_{0} \in  X]]></fr:tex>, and <fr:tex
display="inline"><![CDATA[h\colon X\to X]]></fr:tex> be a function.
  For each <fr:tex
display="inline"><![CDATA[n \in  \mathbb {N}]]></fr:tex>, a function <fr:tex
display="inline"><![CDATA[g\colon s(n)\to X]]></fr:tex> is called an <fr:em><fr:strong><fr:tex
display="inline"><![CDATA[n]]></fr:tex>-germ</fr:strong></fr:em> if it satisfies the following conditions:
  <fr:ul><fr:li><fr:tex
display="inline"><![CDATA[g(0) = x_{0}]]></fr:tex>;</fr:li>
    <fr:li><fr:tex
display="inline"><![CDATA[g(s(m)) = h(g(m))]]></fr:tex> for all <fr:tex
display="inline"><![CDATA[m < n]]></fr:tex>.</fr:li></fr:ul></fr:p></fr:mainmatter><fr:backmatter /></fr:tree><fr:tree
toc="true"
numbered="true"
show-heading="true"
show-metadata="false"
expanded="true"
root="false"
xmlns:fr="http://www.jonmsterling.com/jms-005P.xml"><fr:frontmatter><fr:anchor>381</fr:anchor><fr:addr
type="user">set-0014</fr:addr><fr:route>set-0014.xml</fr:route><fr:title
text="Class-level n-germs">Class-level <fr:tex
display="inline"><![CDATA[n]]></fr:tex>-germs</fr:title><fr:taxon>Definition</fr:taxon><fr:date><fr:year>2024</fr:year><fr:month>10</fr:month><fr:day>21</fr:day></fr:date><fr:authors /></fr:frontmatter><fr:mainmatter><fr:p>Let <fr:tex
display="inline"><![CDATA[\varphi ]]></fr:tex> be a definable mapping with at most <fr:tex
display="inline"><![CDATA[x,y]]></fr:tex> free and <fr:tex
display="inline"><![CDATA[x_{0}]]></fr:tex> be an arbitrary set.
  A <fr:em><fr:strong>class-level <fr:tex
display="inline"><![CDATA[n]]></fr:tex>-germ</fr:strong></fr:em> is a function <fr:tex
display="inline"><![CDATA[g]]></fr:tex> with <fr:tex
display="inline"><![CDATA[\mathsf {dom}(g) = s(n)]]></fr:tex> such that the following two conditions are satisfied.
  <fr:ul><fr:li><fr:tex
display="inline"><![CDATA[g(0) = x_{0}]]></fr:tex>;</fr:li>
    <fr:li><fr:tex
display="inline"><![CDATA[\varphi (g(m),g(s(m)))]]></fr:tex> for all <fr:tex
display="inline"><![CDATA[m < n]]></fr:tex>.</fr:li></fr:ul></fr:p></fr:mainmatter><fr:backmatter /></fr:tree><fr:tree
toc="true"
numbered="true"
show-heading="true"
show-metadata="false"
expanded="true"
root="false"
xmlns:fr="http://www.jonmsterling.com/jms-005P.xml"><fr:frontmatter><fr:anchor>382</fr:anchor><fr:addr
type="user">set-0011</fr:addr><fr:route>set-0011.xml</fr:route><fr:title
text="Existence and uniqueness of n-germ">Existence and uniqueness of <fr:link
type="local"
href="set-0010.xml"
addr="set-0010"
title="Germs"><fr:tex
display="inline"><![CDATA[n]]></fr:tex>-germ</fr:link></fr:title><fr:taxon>Proposition</fr:taxon><fr:date><fr:year>2024</fr:year><fr:month>10</fr:month><fr:day>21</fr:day></fr:date><fr:authors /></fr:frontmatter><fr:mainmatter><fr:p>Let <fr:tex
display="inline"><![CDATA[X]]></fr:tex> be a set equipped with a distinguished element <fr:tex
display="inline"><![CDATA[x_{0} \in  X]]></fr:tex> and an endofunction <fr:tex
display="inline"><![CDATA[h\colon X\to X]]></fr:tex>.
  For each <fr:tex
display="inline"><![CDATA[n \in  \mathbb {N}]]></fr:tex>, there is a unique <fr:tex
display="inline"><![CDATA[n]]></fr:tex>-germ.</fr:p>
    
      
      <fr:tree
toc="false"
numbered="true"
show-heading="true"
show-metadata="false"
expanded="true"
root="false"
xmlns:fr="http://www.jonmsterling.com/jms-005P.xml"><fr:frontmatter><fr:anchor>383</fr:anchor><fr:addr
type="machine">#250</fr:addr><fr:route>unstable-250.xml</fr:route><fr:taxon>Proof</fr:taxon><fr:date><fr:year>2024</fr:year><fr:month>10</fr:month><fr:day>21</fr:day></fr:date><fr:authors /></fr:frontmatter><fr:mainmatter>
  <fr:p>We proceed by induction on <fr:tex
display="inline"><![CDATA[n]]></fr:tex>.
    In the base case, we define the function <fr:tex
display="inline"><![CDATA[g_{0}\colon s(0)\to X]]></fr:tex> by <fr:tex
display="inline"><![CDATA[g(0) = x_{0}]]></fr:tex>.
    Note that this is a <fr:tex
display="inline"><![CDATA[0]]></fr:tex>-germ and uniqueness is an immediate consequence of <fr:ref
addr="set-000S"
href="set-000S.xml"
taxon="Proposition" />.</fr:p>
  <fr:p>In the induction step, the induction hypothesis says there is a unique <fr:tex
display="inline"><![CDATA[n]]></fr:tex>-germ <fr:tex
display="inline"><![CDATA[g_{n}\colon s(n)\to X]]></fr:tex>.
    Consider the function <fr:tex
display="inline"><![CDATA[g_{s(n)}\colon s(s(n))\to X]]></fr:tex> defined by
    <fr:tex
display="block"><![CDATA[       g_{s(n)}(k) =       \begin {cases}         h(g_{n}(n)) & \text {if $k = s(n)$}\\         g_{n}(k) & \text {if $k < s(n)$}       \end {cases}     ]]></fr:tex></fr:p>
  <fr:p>By direct computation, we have <fr:tex
display="inline"><![CDATA[g_{s(n)}(0) = g_{n}(0) = x_{0}]]></fr:tex>.
    For any <fr:tex
display="inline"><![CDATA[m < s(n)]]></fr:tex>, we have <fr:tex
display="inline"><![CDATA[m < n]]></fr:tex> or <fr:tex
display="inline"><![CDATA[m = n]]></fr:tex>.
    In the former case, we have <fr:tex
display="inline"><![CDATA[g_{s(n)}(s(m)) = g_{n}(s(m)) = h(g_{n}(m))]]></fr:tex>.
    In the latter case, we have <fr:tex
display="inline"><![CDATA[g_{s(n)}(s(m)) = h(g_{n}(m)) = h(g_{s(n)}(m))]]></fr:tex>.</fr:p>
  <fr:p>It remains to show that <fr:tex
display="inline"><![CDATA[g_{s(n)}]]></fr:tex> is unique.
    Note that the domain restriction of any <fr:tex
display="inline"><![CDATA[s(n)]]></fr:tex>-germ to <fr:tex
display="inline"><![CDATA[s(n)]]></fr:tex> is an <fr:tex
display="inline"><![CDATA[n]]></fr:tex>-germ.
    By the induction hypothesis, <fr:tex
display="inline"><![CDATA[n]]></fr:tex>-germ exists uniquely.
    Thus, picking <fr:tex
display="inline"><![CDATA[g_{s(n)}(s(n)) = h(g_{n}(n))]]></fr:tex> is the only way to extend the unique <fr:tex
display="inline"><![CDATA[n]]></fr:tex>-germ to an <fr:tex
display="inline"><![CDATA[s(n)]]></fr:tex>-germ.</fr:p>
</fr:mainmatter><fr:backmatter /></fr:tree>
    
  </fr:mainmatter><fr:backmatter /></fr:tree><fr:tree
toc="true"
numbered="true"
show-heading="true"
show-metadata="false"
expanded="true"
root="false"
xmlns:fr="http://www.jonmsterling.com/jms-005P.xml"><fr:frontmatter><fr:anchor>384</fr:anchor><fr:addr
type="user">set-0012</fr:addr><fr:route>set-0012.xml</fr:route><fr:title
text="Natural numbers are the initial discrete dynamical system"><fr:link
type="local"
href="set-000V.xml"
addr="set-000V"
title="Natural numbers">Natural numbers</fr:link> are the initial discrete dynamical system</fr:title><fr:taxon>Proposition</fr:taxon><fr:date><fr:year>2024</fr:year><fr:month>10</fr:month><fr:day>21</fr:day></fr:date><fr:authors /></fr:frontmatter><fr:mainmatter><fr:p>Let <fr:tex
display="inline"><![CDATA[X]]></fr:tex> be a set equipped with a distinguished element <fr:tex
display="inline"><![CDATA[x_{0} \in  X]]></fr:tex> and an endofunction <fr:tex
display="inline"><![CDATA[h\colon X\to X]]></fr:tex>.
  Then there is a unique function <fr:tex
display="inline"><![CDATA[f\colon \mathbb {N}\to X]]></fr:tex> such that
  <fr:ul><fr:li><fr:tex
display="inline"><![CDATA[f(0) = x_{0}]]></fr:tex>;</fr:li>
    <fr:li><fr:tex
display="inline"><![CDATA[f(s(n)) = h(f(n))]]></fr:tex>.</fr:li></fr:ul></fr:p>
    
      
      <fr:tree
toc="false"
numbered="true"
show-heading="true"
show-metadata="false"
expanded="true"
root="false"
xmlns:fr="http://www.jonmsterling.com/jms-005P.xml"><fr:frontmatter><fr:anchor>385</fr:anchor><fr:addr
type="machine">#249</fr:addr><fr:route>unstable-249.xml</fr:route><fr:taxon>Proof</fr:taxon><fr:date><fr:year>2024</fr:year><fr:month>10</fr:month><fr:day>21</fr:day></fr:date><fr:authors /></fr:frontmatter><fr:mainmatter>
  By <fr:ref
addr="set-0011"
href="set-0011.xml"
taxon="Proposition" />, for each <fr:tex
display="inline"><![CDATA[n \in  \mathbb {N}]]></fr:tex>, an <fr:tex
display="inline"><![CDATA[n]]></fr:tex>-germ exists uniquely.
  Consider
  <fr:tex
display="block"><![CDATA[     f = \bigcup {\mathopen {}\{g \in  \mathcal {P}(\mathbb {N} \times  X)\colon \exists n \in  \mathbb {N}.\mkern 5mu\text {$g$ is an $n$-germ}\}\mathclose {}}.   ]]></fr:tex>
  By construction, each <fr:tex
display="inline"><![CDATA[s(n)]]></fr:tex>-germ is the unique extension of <fr:tex
display="inline"><![CDATA[n]]></fr:tex>-germ.
  Thus, it follows that <fr:tex
display="inline"><![CDATA[f]]></fr:tex> is a function.
  By an easy induction on <fr:tex
display="inline"><![CDATA[n]]></fr:tex>, one sees that <fr:tex
display="inline"><![CDATA[f]]></fr:tex> is the unique function with the required properties.
</fr:mainmatter><fr:backmatter /></fr:tree>
    
  </fr:mainmatter><fr:backmatter /></fr:tree><fr:tree
toc="true"
numbered="true"
show-heading="true"
show-metadata="false"
expanded="true"
root="false"
xmlns:fr="http://www.jonmsterling.com/jms-005P.xml"><fr:frontmatter><fr:anchor>386</fr:anchor><fr:addr
type="user">set-0013</fr:addr><fr:route>set-0013.xml</fr:route><fr:title
text="Class recursion">Class recursion</fr:title><fr:taxon>Proposition</fr:taxon><fr:date><fr:year>2024</fr:year><fr:month>10</fr:month><fr:day>21</fr:day></fr:date><fr:authors /></fr:frontmatter><fr:mainmatter><fr:p>Let <fr:tex
display="inline"><![CDATA[\varphi ]]></fr:tex> be a definable mapping with at most <fr:tex
display="inline"><![CDATA[x,y]]></fr:tex> free.
  Then for any set <fr:tex
display="inline"><![CDATA[x_{0}]]></fr:tex> there is a unique function <fr:tex
display="inline"><![CDATA[f]]></fr:tex> with <fr:tex
display="inline"><![CDATA[\mathsf {dom}(f) = \mathbb {N}]]></fr:tex> such that
  <fr:ul><fr:li><fr:tex
display="inline"><![CDATA[f(0) = x_{0}]]></fr:tex>;</fr:li>
    <fr:li><fr:tex
display="inline"><![CDATA[\varphi (f(n),f(s(n)))]]></fr:tex> for every <fr:tex
display="inline"><![CDATA[n \in  \mathbb {N}]]></fr:tex>.</fr:li></fr:ul></fr:p>
    
      
      <fr:tree
toc="false"
numbered="true"
show-heading="true"
show-metadata="false"
expanded="true"
root="false"
xmlns:fr="http://www.jonmsterling.com/jms-005P.xml"><fr:frontmatter><fr:anchor>387</fr:anchor><fr:addr
type="machine">#248</fr:addr><fr:route>unstable-248.xml</fr:route><fr:taxon>Proof</fr:taxon><fr:date><fr:year>2024</fr:year><fr:month>10</fr:month><fr:day>21</fr:day></fr:date><fr:authors /></fr:frontmatter><fr:mainmatter>
  The proof is similar to that of <fr:ref
addr="set-0012"
href="set-0012.xml"
taxon="Proposition" />.
  By <fr:ref
addr="set-0015"
href="set-0015.xml"
taxon="Proposition" />, each <fr:tex
display="inline"><![CDATA[n]]></fr:tex>-germ exists uniquely.
  This gives a definable mapping <fr:tex
display="inline"><![CDATA[\psi (n,g) := (n \in  \mathbb {N} \Rightarrow  g~\text {is an $n$-germ}) \wedge  (n \notin  \mathbb {N} \Rightarrow  g = \varnothing )]]></fr:tex>.
  By <fr:link
type="local"
href="set-0008.xml"
addr="set-0008"
title="Axiom schema of replacement">replacement</fr:link>, we define
  <fr:tex
display="block"><![CDATA[     f := {\mathopen {}\{g\colon n \in  \mathbb {N}, g~\text {is an $n$-germ}\}\mathclose {}}.   ]]></fr:tex>
</fr:mainmatter><fr:backmatter /></fr:tree>
    
  </fr:mainmatter><fr:backmatter /></fr:tree></fr:mainmatter><fr:backmatter /></fr:tree>
</fr:mainmatter><fr:backmatter /></fr:tree></fr:mainmatter><fr:backmatter /></fr:tree><fr:tree
toc="false"
numbered="false"
show-heading="true"
show-metadata="false"
expanded="true"
root="false"
xmlns:fr="http://www.jonmsterling.com/jms-005P.xml"><fr:frontmatter><fr:title
text="Backlinks">Backlinks</fr:title><fr:authors /></fr:frontmatter><fr:mainmatter><fr:tree
toc="true"
numbered="false"
show-heading="true"
show-metadata="true"
expanded="false"
root="false"
xmlns:fr="http://www.jonmsterling.com/jms-005P.xml"><fr:frontmatter><fr:anchor>505</fr:anchor><fr:addr
type="user">set-0011</fr:addr><fr:route>set-0011.xml</fr:route><fr:title
text="Existence and uniqueness of n-germ">Existence and uniqueness of <fr:link
type="local"
href="set-0010.xml"
addr="set-0010"
title="Germs"><fr:tex
display="inline"><![CDATA[n]]></fr:tex>-germ</fr:link></fr:title><fr:taxon>Proposition</fr:taxon><fr:date><fr:year>2024</fr:year><fr:month>10</fr:month><fr:day>21</fr:day></fr:date><fr:authors /></fr:frontmatter><fr:mainmatter><fr:p>Let <fr:tex
display="inline"><![CDATA[X]]></fr:tex> be a set equipped with a distinguished element <fr:tex
display="inline"><![CDATA[x_{0} \in  X]]></fr:tex> and an endofunction <fr:tex
display="inline"><![CDATA[h\colon X\to X]]></fr:tex>.
  For each <fr:tex
display="inline"><![CDATA[n \in  \mathbb {N}]]></fr:tex>, there is a unique <fr:tex
display="inline"><![CDATA[n]]></fr:tex>-germ.</fr:p>
    
      
      <fr:tree
toc="false"
numbered="true"
show-heading="true"
show-metadata="false"
expanded="true"
root="false"
xmlns:fr="http://www.jonmsterling.com/jms-005P.xml"><fr:frontmatter><fr:anchor>383</fr:anchor><fr:addr
type="machine">#250</fr:addr><fr:route>unstable-250.xml</fr:route><fr:taxon>Proof</fr:taxon><fr:date><fr:year>2024</fr:year><fr:month>10</fr:month><fr:day>21</fr:day></fr:date><fr:authors /></fr:frontmatter><fr:mainmatter>
  <fr:p>We proceed by induction on <fr:tex
display="inline"><![CDATA[n]]></fr:tex>.
    In the base case, we define the function <fr:tex
display="inline"><![CDATA[g_{0}\colon s(0)\to X]]></fr:tex> by <fr:tex
display="inline"><![CDATA[g(0) = x_{0}]]></fr:tex>.
    Note that this is a <fr:tex
display="inline"><![CDATA[0]]></fr:tex>-germ and uniqueness is an immediate consequence of <fr:ref
addr="set-000S"
href="set-000S.xml"
taxon="Proposition" />.</fr:p>
  <fr:p>In the induction step, the induction hypothesis says there is a unique <fr:tex
display="inline"><![CDATA[n]]></fr:tex>-germ <fr:tex
display="inline"><![CDATA[g_{n}\colon s(n)\to X]]></fr:tex>.
    Consider the function <fr:tex
display="inline"><![CDATA[g_{s(n)}\colon s(s(n))\to X]]></fr:tex> defined by
    <fr:tex
display="block"><![CDATA[       g_{s(n)}(k) =       \begin {cases}         h(g_{n}(n)) & \text {if $k = s(n)$}\\         g_{n}(k) & \text {if $k < s(n)$}       \end {cases}     ]]></fr:tex></fr:p>
  <fr:p>By direct computation, we have <fr:tex
display="inline"><![CDATA[g_{s(n)}(0) = g_{n}(0) = x_{0}]]></fr:tex>.
    For any <fr:tex
display="inline"><![CDATA[m < s(n)]]></fr:tex>, we have <fr:tex
display="inline"><![CDATA[m < n]]></fr:tex> or <fr:tex
display="inline"><![CDATA[m = n]]></fr:tex>.
    In the former case, we have <fr:tex
display="inline"><![CDATA[g_{s(n)}(s(m)) = g_{n}(s(m)) = h(g_{n}(m))]]></fr:tex>.
    In the latter case, we have <fr:tex
display="inline"><![CDATA[g_{s(n)}(s(m)) = h(g_{n}(m)) = h(g_{s(n)}(m))]]></fr:tex>.</fr:p>
  <fr:p>It remains to show that <fr:tex
display="inline"><![CDATA[g_{s(n)}]]></fr:tex> is unique.
    Note that the domain restriction of any <fr:tex
display="inline"><![CDATA[s(n)]]></fr:tex>-germ to <fr:tex
display="inline"><![CDATA[s(n)]]></fr:tex> is an <fr:tex
display="inline"><![CDATA[n]]></fr:tex>-germ.
    By the induction hypothesis, <fr:tex
display="inline"><![CDATA[n]]></fr:tex>-germ exists uniquely.
    Thus, picking <fr:tex
display="inline"><![CDATA[g_{s(n)}(s(n)) = h(g_{n}(n))]]></fr:tex> is the only way to extend the unique <fr:tex
display="inline"><![CDATA[n]]></fr:tex>-germ to an <fr:tex
display="inline"><![CDATA[s(n)]]></fr:tex>-germ.</fr:p>
</fr:mainmatter><fr:backmatter /></fr:tree>
    
  </fr:mainmatter><fr:backmatter /></fr:tree></fr:mainmatter><fr:backmatter /></fr:tree><fr:tree
toc="false"
numbered="false"
show-heading="true"
show-metadata="false"
expanded="true"
root="false"
xmlns:fr="http://www.jonmsterling.com/jms-005P.xml"><fr:frontmatter><fr:title
text="Related">Related</fr:title><fr:authors /></fr:frontmatter><fr:mainmatter><fr:tree
toc="true"
numbered="false"
show-heading="true"
show-metadata="true"
expanded="false"
root="false"
xmlns:fr="http://www.jonmsterling.com/jms-005P.xml"><fr:frontmatter><fr:anchor>506</fr:anchor><fr:addr
type="user">set-000R</fr:addr><fr:route>set-000R.xml</fr:route><fr:title
text="Function">Function</fr:title><fr:taxon>Definition</fr:taxon><fr:date><fr:year>2024</fr:year><fr:month>10</fr:month><fr:day>20</fr:day></fr:date><fr:authors /></fr:frontmatter><fr:mainmatter><fr:p>A <fr:em><fr:strong>function</fr:strong></fr:em> <fr:tex
display="inline"><![CDATA[f\colon A\to B]]></fr:tex> is a <fr:link
type="local"
href="set-000N.xml"
addr="set-000N"
title="Total relation">total</fr:link> and <fr:link
type="local"
href="set-000O.xml"
addr="set-000O"
title="Functional relation">functional</fr:link> <fr:link
type="local"
href="set-000M.xml"
addr="set-000M"
title="Relation">relation</fr:link> <fr:tex
display="inline"><![CDATA[f\colon A\nrightarrow B]]></fr:tex>.
  We define <fr:tex
display="inline"><![CDATA[B^{A} := {\mathopen {}\{f \in  \mathcal {P}(A \times  B)\colon \text {$f$ is a function}\}\mathclose {}}]]></fr:tex>.</fr:p></fr:mainmatter><fr:backmatter /></fr:tree><fr:tree
toc="true"
numbered="false"
show-heading="true"
show-metadata="true"
expanded="false"
root="false"
xmlns:fr="http://www.jonmsterling.com/jms-005P.xml"><fr:frontmatter><fr:anchor>507</fr:anchor><fr:addr
type="user">set-000O</fr:addr><fr:route>set-000O.xml</fr:route><fr:title
text="Functional relation">Functional <fr:link
type="local"
href="set-000M.xml"
addr="set-000M"
title="Relation">relation</fr:link></fr:title><fr:taxon>Definition</fr:taxon><fr:date><fr:year>2024</fr:year><fr:month>10</fr:month><fr:day>20</fr:day></fr:date><fr:authors /></fr:frontmatter><fr:mainmatter><fr:p>A relation <fr:tex
display="inline"><![CDATA[R\colon A\nrightarrow B]]></fr:tex> is <fr:em><fr:strong>functional</fr:strong></fr:em> if for any <fr:tex
display="inline"><![CDATA[(a,b),(c,d) \in  R]]></fr:tex> if <fr:tex
display="inline"><![CDATA[a = c]]></fr:tex> then <fr:tex
display="inline"><![CDATA[b = d]]></fr:tex>.</fr:p></fr:mainmatter><fr:backmatter /></fr:tree><fr:tree
toc="true"
numbered="false"
show-heading="true"
show-metadata="true"
expanded="false"
root="false"
xmlns:fr="http://www.jonmsterling.com/jms-005P.xml"><fr:frontmatter><fr:anchor>508</fr:anchor><fr:addr
type="user">set-000N</fr:addr><fr:route>set-000N.xml</fr:route><fr:title
text="Total relation">Total <fr:link
type="local"
href="set-000M.xml"
addr="set-000M"
title="Relation">relation</fr:link></fr:title><fr:taxon>Definition</fr:taxon><fr:date><fr:year>2024</fr:year><fr:month>10</fr:month><fr:day>20</fr:day></fr:date><fr:authors /></fr:frontmatter><fr:mainmatter><fr:p>A relation <fr:tex
display="inline"><![CDATA[R\colon A\nrightarrow B]]></fr:tex> is <fr:em><fr:strong>total</fr:strong></fr:em> if <fr:tex
display="inline"><![CDATA[\mathsf {supp}(R) = A]]></fr:tex>.
  In other words, for all <fr:tex
display="inline"><![CDATA[a \in  A]]></fr:tex> there exists <fr:tex
display="inline"><![CDATA[b \in  B]]></fr:tex> such that <fr:tex
display="inline"><![CDATA[(a,b) \in  R]]></fr:tex>.</fr:p></fr:mainmatter><fr:backmatter /></fr:tree><fr:tree
toc="true"
numbered="false"
show-heading="true"
show-metadata="true"
expanded="false"
root="false"
xmlns:fr="http://www.jonmsterling.com/jms-005P.xml"><fr:frontmatter><fr:anchor>509</fr:anchor><fr:addr
type="user">set-0001</fr:addr><fr:route>set-0001.xml</fr:route><fr:title
text="Axiom of extensionality">Axiom of extensionality</fr:title><fr:taxon>Axiom</fr:taxon><fr:date><fr:year>2024</fr:year><fr:month>9</fr:month><fr:day>15</fr:day></fr:date><fr:authors /></fr:frontmatter><fr:mainmatter><fr:p>Two sets are equal iff they have the same elements.</fr:p><fr:tex
display="block"><![CDATA[   \forall x,y.\mkern 5mux = y \Leftrightarrow  \forall z.\mkern 5muz \in  x \Leftrightarrow  z \in  y ]]></fr:tex></fr:mainmatter><fr:backmatter /></fr:tree></fr:mainmatter><fr:backmatter /></fr:tree></fr:backmatter></fr:tree>